[
    {
        "external_author_id": "895000000000000000",
        "author": "ANCARICTRS",
        "content": "RT ACTBrigitte: Interesting how everyone claiming Trump is a racist because Duke endorsed him never opened their mouth when Farrakhan endor\u2026",
        "region": "Unknown",
        "language": "English",
        "publish_date": "8/18/2017 1:22",
        "harvested_date": "8/18/2017 1:22",
        "following": "1015",
        "followers": "98",
        "updates": "205",
        "post_type": "",
        "account_type": "Right",
        "retweet": "0",
        "account_category": "RightTroll",
        "new_june_2018": "0",
        "alt_external_id": "894805867853488128",
        "tweet_id": "898354311616483328",
        "article_url": "http://twitter.com/894805867853488128/statuses/898354311616483328",
        "tco1_step1": "",
        "tco2_step1": "",
        "tco3_step1": ""
    },
    {
        "external_author_id": "895000000000000000",
        "author": "ANGISDOOYL",
        "content": "RT hrtablaze: I condemn white bigots but I also condemn black &amp; brown ones !   Let's unite under red, white, blue &amp; not under skin color. #\u2026",
        "region": "Unknown",
        "language": "English",
        "publish_date": "8/12/2017 22:47",
        "harvested_date": "8/12/2017 22:47",
        "following": "41",
        "followers": "3",
        "updates": "208",
        "post_type": "",
        "account_type": "Right",
        "retweet": "0",
        "account_category": "RightTroll",
        "new_june_2018": "0",
        "alt_external_id": "894824964431515648",
        "tweet_id": "896503412174585856",
        "article_url": "http://twitter.com/894824964431515648/statuses/896503412174585856",
        "tco1_step1": "",
        "tco2_step1": "",
        "tco3_step1": ""
    },
    {
        "external_author_id": "1686370159",
        "author": "ARCHIEOLIVERS",
        "content": "Former Troy priest Edward Belczak sentenced to 27 months in prison for fraud",
        "region": "United States",
        "language": "English",
        "publish_date": "12/2/2015 9:36",
        "harvested_date": "12/2/2015 9:36",
        "following": "1202",
        "followers": "490",
        "updates": "976",
        "post_type": "",
        "account_type": "Right",
        "retweet": "0",
        "account_category": "RightTroll",
        "new_june_2018": "0",
        "alt_external_id": "1686370159",
        "tweet_id": "671986180200665088",
        "article_url": "http://twitter.com/ArchieOlivers/statuses/671986180200665088",
        "tco1_step1": "",
        "tco2_step1": "",
        "tco3_step1": ""
    },
    {
        "external_author_id": "1699424065",
        "author": "ALEXLOVESSHENNA",
        "content": "The brain does the thinking, but the heart knows more about love than the mind can ever comprehend.",
        "region": "United States",
        "language": "English",
        "publish_date": "5/18/2015 21:35",
        "harvested_date": "5/18/2015 21:35",
        "following": "80",
        "followers": "60",
        "updates": "316",
        "post_type": "",
        "account_type": "Right",
        "retweet": "0",
        "account_category": "RightTroll",
        "new_june_2018": "0",
        "alt_external_id": "1699424065",
        "tweet_id": "600414502723584000",
        "article_url": "http://twitter.com/AlexLovesShenna/statuses/600414502723584000",
        "tco1_step1": "",
        "tco2_step1": "",
        "tco3_step1": ""
    },
    {
        "external_author_id": "2616344667",
        "author": "AMANDAVGREEN",
        "content": "He took the last slice of pizza  #ReasonsToGetDivorced",
        "region": "United States",
        "language": "English",
        "publish_date": "9/21/2016 15:13",
        "harvested_date": "9/21/2016 15:13",
        "following": "2658",
        "followers": "2976",
        "updates": "3704",
        "post_type": "",
        "account_type": "Hashtager",
        "retweet": "0",
        "account_category": "HashtagGamer",
        "new_june_2018": "0",
        "alt_external_id": "2616344667",
        "tweet_id": "778613005734993920",
        "article_url": "http://twitter.com/AmandaVGreen/statuses/778613005734993920",
        "tco1_step1": "",
        "tco2_step1": "",
        "tco3_step1": ""
    },
    {
        "external_author_id": "895000000000000000",
        "author": "AMYYSLEGENTR",
        "content": "cyndilauper What trail did you blaze, seriously?",
        "region": "Unknown",
        "language": "English",
        "publish_date": "8/14/2017 11:10",
        "harvested_date": "8/14/2017 11:10",
        "following": "26",
        "followers": "6",
        "updates": "558",
        "post_type": "",
        "account_type": "Right",
        "retweet": "0",
        "account_category": "RightTroll",
        "new_june_2018": "0",
        "alt_external_id": "894794223207161856",
        "tweet_id": "897052791344160768",
        "article_url": "http://twitter.com/894794223207161856/statuses/897052791344160768",
        "tco1_step1": "",
        "tco2_step1": "",
        "tco3_step1": ""
    },
    {
        "external_author_id": "895000000000000000",
        "author": "ANIIANTRS",
        "content": "RT InGodIDoTrust: As soon as the Debbie Wasserman and Awan Russian story broke, the Media immediately stopped talking about Russian collusi\u2026",
        "region": "Unknown",
        "language": "English",
        "publish_date": "8/16/2017 1:40",
        "harvested_date": "8/16/2017 1:40",
        "following": "38",
        "followers": "6",
        "updates": "1287",
        "post_type": "",
        "account_type": "Right",
        "retweet": "0",
        "account_category": "RightTroll",
        "new_june_2018": "0",
        "alt_external_id": "894845726840283136",
        "tweet_id": "897634125024301056",
        "article_url": "http://twitter.com/894845726840283136/statuses/897634125024301056",
        "tco1_step1": "",
        "tco2_step1": "",
        "tco3_step1": ""
    },
    {
        "external_author_id": "895000000000000000",
        "author": "ANAAISLEC",
        "content": "RT Cernovich: The left has talked about \"blood in the streets\" and military coups for months, they militarized what should be civil discour\u2026",
        "region": "Unknown",
        "language": "English",
        "publish_date": "8/14/2017 17:14",
        "harvested_date": "8/14/2017 17:15",
        "following": "37",
        "followers": "60",
        "updates": "1293",
        "post_type": "",
        "account_type": "Right",
        "retweet": "0",
        "account_category": "RightTroll",
        "new_june_2018": "0",
        "alt_external_id": "894801330912546817",
        "tweet_id": "897144513323569153",
        "article_url": "http://twitter.com/894801330912546817/statuses/897144513323569153",
        "tco1_step1": "",
        "tco2_step1": "",
        "tco3_step1": ""
    },
    {
        "external_author_id": "895000000000000000",
        "author": "ASWWIMMORRIS",
        "content": "winegirl73 ColoradoGirl2A Oh right, forgot my pussy hat!!",
        "region": "Unknown",
        "language": "English",
        "publish_date": "8/12/2017 18:14",
        "harvested_date": "8/12/2017 18:14",
        "following": "0",
        "followers": "0",
        "updates": "186",
        "post_type": "",
        "account_type": "Right",
        "retweet": "0",
        "account_category": "RightTroll",
        "new_june_2018": "0",
        "alt_external_id": "895224264424648704",
        "tweet_id": "896434751812374528",
        "article_url": "http://twitter.com/895224264424648704/statuses/896434751812374528",
        "tco1_step1": "",
        "tco2_step1": "",
        "tco3_step1": ""
    },
    {
        "external_author_id": "895000000000000000",
        "author": "ANAAISLEC",
        "content": "RT Patrici89635327: BarbMuenchen POTUS Anybody for super glue on there mouths! That might really work\ud83d\ude0a\ud83d\ude02",
        "region": "Unknown",
        "language": "English",
        "publish_date": "8/14/2017 2:57",
        "harvested_date": "8/14/2017 2:57",
        "following": "37",
        "followers": "54",
        "updates": "1093",
        "post_type": "",
        "account_type": "Right",
        "retweet": "0",
        "account_category": "RightTroll",
        "new_june_2018": "0",
        "alt_external_id": "894801330912546817",
        "tweet_id": "896928666336337920",
        "article_url": "http://twitter.com/894801330912546817/statuses/896928666336337920",
        "tco1_step1": "",
        "tco2_step1": "",
        "tco3_step1": ""
    },
    {
        "external_author_id": "895000000000000000",
        "author": "ANISILOPE",
        "content": "MMilzman Give these culls a stock tip &amp; they will forget all about Trump while fighting for a phone so they can call their brokers.",
        "region": "United States",
        "language": "English",
        "publish_date": "8/13/2017 4:58",
        "harvested_date": "8/13/2017 4:58",
        "following": "25",
        "followers": "5",
        "updates": "273",
        "post_type": "",
        "account_type": "Right",
        "retweet": "0",
        "account_category": "RightTroll",
        "new_june_2018": "0",
        "alt_external_id": "894835103225880576",
        "tweet_id": "896596740807290880",
        "article_url": "http://twitter.com/894835103225880576/statuses/896596740807290880",
        "tco1_step1": "",
        "tco2_step1": "",
        "tco3_step1": ""
    },
    {
        "external_author_id": "2878166306",
        "author": "ANDYHASHTAGGER",
        "content": "#IWasBlockedFor naked pictures",
        "region": "United States",
        "language": "English",
        "publish_date": "5/12/2016 12:31",
        "harvested_date": "5/12/2016 12:31",
        "following": "17092",
        "followers": "21403",
        "updates": "8848",
        "post_type": "",
        "account_type": "Hashtager",
        "retweet": "0",
        "account_category": "HashtagGamer",
        "new_june_2018": "1",
        "alt_external_id": "2878166306",
        "tweet_id": "730737064841510912",
        "article_url": "http://twitter.com/AndyHashtagger/statuses/730737064841510912",
        "tco1_step1": "",
        "tco2_step1": "",
        "tco3_step1": ""
    },
    {
        "external_author_id": "891000000000000000",
        "author": "AFEELIUTR",
        "content": "#adee RT YvonneMichell16: When God exposes the corruption in DC, it is our responsibility to make sure we vote it out and remove it.\u2026 \u2026",
        "region": "United States",
        "language": "English",
        "publish_date": "7/30/2017 22:14",
        "harvested_date": "7/30/2017 22:14",
        "following": "995",
        "followers": "319",
        "updates": "410",
        "post_type": "",
        "account_type": "Right",
        "retweet": "0",
        "account_category": "RightTroll",
        "new_june_2018": "0",
        "alt_external_id": "891183122305486848",
        "tweet_id": "891784009914736641",
        "article_url": "http://twitter.com/891183122305486848/statuses/891784009914736641",
        "tco1_step1": "",
        "tco2_step1": "",
        "tco3_step1": ""
    },
    {
        "external_author_id": "895000000000000000",
        "author": "AMBERRPAR",
        "content": "RT EnigmaOfCatch22: What a coincidence. Russia narrative is wrecked, North Korea backs down, and suddenly we're back to \"T\u2026 \u2026",
        "region": "Unknown",
        "language": "English",
        "publish_date": "8/16/2017 3:04",
        "harvested_date": "8/16/2017 3:04",
        "following": "22",
        "followers": "7",
        "updates": "867",
        "post_type": "",
        "account_type": "Right",
        "retweet": "0",
        "account_category": "RightTroll",
        "new_june_2018": "0",
        "alt_external_id": "894787222964101120",
        "tweet_id": "897655220485980160",
        "article_url": "http://twitter.com/894787222964101120/statuses/897655220485980160",
        "tco1_step1": "",
        "tco2_step1": "",
        "tco3_step1": ""
    },
    {
        "external_author_id": "2570250275",
        "author": "AIDEN7757",
        "content": "#SlaveryOfSpeech The government should pay more attention to our internal problems!",
        "region": "United States",
        "language": "English",
        "publish_date": "2/25/2015 18:48",
        "harvested_date": "2/25/2015 18:48",
        "following": "260",
        "followers": "37",
        "updates": "336",
        "post_type": "",
        "account_type": "Hashtager",
        "retweet": "0",
        "account_category": "HashtagGamer",
        "new_june_2018": "0",
        "alt_external_id": "2570250275",
        "tweet_id": "570656662723244032",
        "article_url": "http://twitter.com/Aiden7757/statuses/570656662723244032",
        "tco1_step1": "",
        "tco2_step1": "",
        "tco3_step1": ""
    },
    {
        "external_author_id": "2500690416",
        "author": "ANNIEPOSHES",
        "content": "smashed pinky toe #WorstPainEverIn3Words",
        "region": "United States",
        "language": "English",
        "publish_date": "8/24/2016 10:06",
        "harvested_date": "8/24/2016 10:06",
        "following": "1197",
        "followers": "1674",
        "updates": "2428",
        "post_type": "",
        "account_type": "Hashtager",
        "retweet": "0",
        "account_category": "HashtagGamer",
        "new_june_2018": "1",
        "alt_external_id": "2500690416",
        "tweet_id": "768388973815181312",
        "article_url": "http://twitter.com/AnniePoshes/statuses/768388973815181312",
        "tco1_step1": "",
        "tco2_step1": "",
        "tco3_step1": ""
    },
    {
        "external_author_id": "890000000000000000",
        "author": "AMBERLINETR",
        "content": "RT janeyhasmoved: \"Anyone who doesn't love s.44 of our Constitution tonight is a bum\" [I paraphrase]  #MalcolmRoberts #choosingtobelieve #a\u2026",
        "region": "United States",
        "language": "English",
        "publish_date": "7/27/2017 11:47",
        "harvested_date": "7/27/2017 11:55",
        "following": "964",
        "followers": "2",
        "updates": "93",
        "post_type": "",
        "account_type": "Right",
        "retweet": "0",
        "account_category": "RightTroll",
        "new_june_2018": "0",
        "alt_external_id": "890429331373043712",
        "tweet_id": "890539056119074820",
        "article_url": "http://twitter.com/890429331373043712/statuses/890539056119074820",
        "tco1_step1": "",
        "tco2_step1": "",
        "tco3_step1": ""
    },
    {
        "external_author_id": "2500690416",
        "author": "ANNIEPOSHES",
        "content": "Trying to save the Star Wars prequels only to find out YOU wrote the prequels  #TimeTravelerProblems",
        "region": "United States",
        "language": "English",
        "publish_date": "7/30/2016 10:09",
        "harvested_date": "7/30/2016 10:11",
        "following": "2367",
        "followers": "1292",
        "updates": "1763",
        "post_type": "",
        "account_type": "Hashtager",
        "retweet": "0",
        "account_category": "HashtagGamer",
        "new_june_2018": "1",
        "alt_external_id": "2500690416",
        "tweet_id": "759330122273021952",
        "article_url": "http://twitter.com/AnniePoshes/statuses/759330122273021952",
        "tco1_step1": "",
        "tco2_step1": "",
        "tco3_step1": ""
    },
    {
        "external_author_id": "2616344667",
        "author": "AMANDAVGREEN",
        "content": "#ValentinesDayIn3Words I hate #ValentinesDay",
        "region": "United States",
        "language": "English",
        "publish_date": "2/8/2017 15:43",
        "harvested_date": "2/8/2017 15:46",
        "following": "4416",
        "followers": "5704",
        "updates": "6151",
        "post_type": "",
        "account_type": "Hashtager",
        "retweet": "0",
        "account_category": "HashtagGamer",
        "new_june_2018": "0",
        "alt_external_id": "2616344667",
        "tweet_id": "829355067820146688",
        "article_url": "http://twitter.com/2616344667/statuses/829355067820146688",
        "tco1_step1": "",
        "tco2_step1": "",
        "tco3_step1": ""
    },
    {
        "external_author_id": "2570250275",
        "author": "AIDEN7757",
        "content": "My Love Has Got u So Blind That u Couldn't Pick Amy Winehouse Out Of a Line Up  \u2013 Eminem",
        "region": "United States",
        "language": "English",
        "publish_date": "3/18/2015 10:03",
        "harvested_date": "3/18/2015 10:03",
        "following": "260",
        "followers": "31",
        "updates": "654",
        "post_type": "",
        "account_type": "Hashtager",
        "retweet": "0",
        "account_category": "HashtagGamer",
        "new_june_2018": "0",
        "alt_external_id": "2570250275",
        "tweet_id": "578134540826206209",
        "article_url": "http://twitter.com/Aiden7757/statuses/578134540826206209",
        "tco1_step1": "",
        "tco2_step1": "",
        "tco3_step1": ""
    },
    {
        "external_author_id": "895000000000000000",
        "author": "ANDEERLWR",
        "content": "RT Texasnana50: trumpiowa TrumpFL GOP POTUS GOPChairwoman Hope the RNC sees this.  Great poll. Tired of the news showing low polls for our \u2026",
        "region": "United States",
        "language": "English",
        "publish_date": "8/8/2017 22:11",
        "harvested_date": "8/8/2017 22:11",
        "following": "21",
        "followers": "2",
        "updates": "62",
        "post_type": "",
        "account_type": "Right",
        "retweet": "0",
        "account_category": "RightTroll",
        "new_june_2018": "0",
        "alt_external_id": "894808551574695937",
        "tweet_id": "895044787727978497",
        "article_url": "http://twitter.com/894808551574695937/statuses/895044787727978497",
        "tco1_step1": "",
        "tco2_step1": "",
        "tco3_step1": ""
    },
    {
        "external_author_id": "1529934134",
        "author": "ANN1EMCCONNELL",
        "content": "#StopIslam #IslamKills #SyrianRefugees ARE TERRORISTS from #ISIS",
        "region": "United States",
        "language": "English",
        "publish_date": "3/22/2016 19:11",
        "harvested_date": "3/22/2016 19:17",
        "following": "71",
        "followers": "56",
        "updates": "117",
        "post_type": "",
        "account_type": "Right",
        "retweet": "0",
        "account_category": "RightTroll",
        "new_june_2018": "1",
        "alt_external_id": "1529934134",
        "tweet_id": "712355917321216001",
        "article_url": "http://twitter.com/Ann1eMcconnell/statuses/712355917321216001",
        "tco1_step1": "",
        "tco2_step1": "",
        "tco3_step1": ""
    },
    {
        "external_author_id": "2616344667",
        "author": "AMANDAVGREEN",
        "content": "Peace. Comfort. Family  #ChristmasIn3Words",
        "region": "United States",
        "language": "English",
        "publish_date": "12/21/2015 15:00",
        "harvested_date": "12/21/2015 15:01",
        "following": "1169",
        "followers": "1169",
        "updates": "1372",
        "post_type": "",
        "account_type": "Hashtager",
        "retweet": "0",
        "account_category": "HashtagGamer",
        "new_june_2018": "0",
        "alt_external_id": "2616344667",
        "tweet_id": "678953292794363904",
        "article_url": "http://twitter.com/AmandaVGreen/statuses/678953292794363904",
        "tco1_step1": "",
        "tco2_step1": "",
        "tco3_step1": ""
    },
    {
        "external_author_id": "2487536839",
        "author": "ALW_ILL",
        "content": "Wish the candidates would stop arguing with each other and say something reasonable about #ActOnClimate #DemDebate #DemnDebate",
        "region": "United States",
        "language": "English",
        "publish_date": "11/15/2015 3:30",
        "harvested_date": "11/15/2015 3:30",
        "following": "110",
        "followers": "30",
        "updates": "213",
        "post_type": "",
        "account_type": "Right",
        "retweet": "0",
        "account_category": "RightTroll",
        "new_june_2018": "0",
        "alt_external_id": "2487536839",
        "tweet_id": "665733568274956288",
        "article_url": "http://twitter.com/AlW_iLL/statuses/665733568274956288",
        "tco1_step1": "",
        "tco2_step1": "",
        "tco3_step1": ""
    },
    {
        "external_author_id": "893000000000000000",
        "author": "ALEXXDRTRR",
        "content": "RT stranahan: Super simple scandal: despite condemning neo-Nazis in Charlottesville, McCain Clinton and Obama supported them in Ukraine doi\u2026",
        "region": "Unknown",
        "language": "English",
        "publish_date": "8/14/2017 5:35",
        "harvested_date": "8/14/2017 5:35",
        "following": "34",
        "followers": "6",
        "updates": "842",
        "post_type": "",
        "account_type": "Right",
        "retweet": "0",
        "account_category": "RightTroll",
        "new_june_2018": "0",
        "alt_external_id": "893397699579576321",
        "tweet_id": "896968476056846337",
        "article_url": "http://twitter.com/893397699579576321/statuses/896968476056846337",
        "tco1_step1": "",
        "tco2_step1": "",
        "tco3_step1": ""
    },
    {
        "external_author_id": "891000000000000000",
        "author": "AFEELIUTR",
        "content": "#adee RT hidehunt1: POTUS We don't pay people to come. We show up with our Stars and Stripes and \ud83d\udcaf support for the one man who truly i\u2026 \u2026",
        "region": "United States",
        "language": "English",
        "publish_date": "7/30/2017 21:10",
        "harvested_date": "7/30/2017 21:10",
        "following": "995",
        "followers": "311",
        "updates": "301",
        "post_type": "",
        "account_type": "Right",
        "retweet": "0",
        "account_category": "RightTroll",
        "new_june_2018": "0",
        "alt_external_id": "891183122305486848",
        "tweet_id": "891767891359653888",
        "article_url": "http://twitter.com/891183122305486848/statuses/891767891359653888",
        "tco1_step1": "",
        "tco2_step1": "",
        "tco3_step1": ""
    },
    {
        "external_author_id": "895000000000000000",
        "author": "ANIIANTRS",
        "content": "RT InGodIDoTrust: Please stop talking about the lesbians in pantsuits!  They have enough trouble trying to desire which bathroom to use",
        "region": "Unknown",
        "language": "English",
        "publish_date": "8/16/2017 14:23",
        "harvested_date": "8/16/2017 14:23",
        "following": "38",
        "followers": "6",
        "updates": "1576",
        "post_type": "",
        "account_type": "Right",
        "retweet": "0",
        "account_category": "RightTroll",
        "new_june_2018": "0",
        "alt_external_id": "894845726840283136",
        "tweet_id": "897826130690027520",
        "article_url": "http://twitter.com/894845726840283136/statuses/897826130690027520",
        "tco1_step1": "",
        "tco2_step1": "",
        "tco3_step1": ""
    },
    {
        "external_author_id": "1657833811",
        "author": "ADRIENNE_GG",
        "content": "She's the giver I wish I could be, and the stealer of the covers. #BradPaisley",
        "region": "United States",
        "language": "English",
        "publish_date": "2/8/2015 15:16",
        "harvested_date": "2/8/2015 15:16",
        "following": "265",
        "followers": "122",
        "updates": "287",
        "post_type": "",
        "account_type": "Hashtager",
        "retweet": "0",
        "account_category": "HashtagGamer",
        "new_june_2018": "0",
        "alt_external_id": "1657833811",
        "tweet_id": "564442695565709312",
        "article_url": "http://twitter.com/Adrienne_GG/statuses/564442695565709312",
        "tco1_step1": "",
        "tco2_step1": "",
        "tco3_step1": ""
    },
    {
        "external_author_id": "895000000000000000",
        "author": "ASWWIMMORRIS",
        "content": "RT LainaCaldwell: 3lectric5heep Kayjo45002058 I call for Letterman to stay retired!",
        "region": "Unknown",
        "language": "English",
        "publish_date": "8/18/2017 19:55",
        "harvested_date": "8/18/2017 19:55",
        "following": "695",
        "followers": "23",
        "updates": "753",
        "post_type": "",
        "account_type": "Right",
        "retweet": "0",
        "account_category": "RightTroll",
        "new_june_2018": "0",
        "alt_external_id": "895224264424648704",
        "tweet_id": "898634445481164800",
        "article_url": "http://twitter.com/895224264424648704/statuses/898634445481164800",
        "tco1_step1": "",
        "tco2_step1": "",
        "tco3_step1": ""
    },
    {
        "external_author_id": "895000000000000000",
        "author": "ANAAISLEC",
        "content": "RT Cynthia7_7: BarbMuenchen seems like the current approach is to erase our nation's history.",
        "region": "Unknown",
        "language": "English",
        "publish_date": "8/17/2017 13:30",
        "harvested_date": "8/17/2017 13:30",
        "following": "1013",
        "followers": "153",
        "updates": "2296",
        "post_type": "",
        "account_type": "Right",
        "retweet": "0",
        "account_category": "RightTroll",
        "new_june_2018": "0",
        "alt_external_id": "894801330912546817",
        "tweet_id": "898175259773480961",
        "article_url": "http://twitter.com/894801330912546817/statuses/898175259773480961",
        "tco1_step1": "",
        "tco2_step1": "",
        "tco3_step1": ""
    },
    {
        "external_author_id": "895000000000000000",
        "author": "ANDEERLWR",
        "content": "dapsixer GOP POTUS GOPChairwoman Primary these GOP candidates",
        "region": "United States",
        "language": "English",
        "publish_date": "8/8/2017 22:03",
        "harvested_date": "8/8/2017 22:03",
        "following": "21",
        "followers": "2",
        "updates": "60",
        "post_type": "",
        "account_type": "Right",
        "retweet": "0",
        "account_category": "RightTroll",
        "new_june_2018": "0",
        "alt_external_id": "894808551574695937",
        "tweet_id": "895042735341801472",
        "article_url": "http://twitter.com/894808551574695937/statuses/895042735341801472",
        "tco1_step1": "",
        "tco2_step1": "",
        "tco3_step1": ""
    },
    {
        "external_author_id": "1652138929",
        "author": "ACEJINEV",
        "content": "These events make me hysteric!!! That is a total catastrophe!!!! #phosphorusdisaster",
        "region": "Unknown",
        "language": "English",
        "publish_date": "3/10/2015 20:48",
        "harvested_date": "3/10/2015 20:48",
        "following": "265",
        "followers": "89",
        "updates": "252",
        "post_type": "",
        "account_type": "Left",
        "retweet": "0",
        "account_category": "LeftTroll",
        "new_june_2018": "0",
        "alt_external_id": "1652138929",
        "tweet_id": "575397915285405696",
        "article_url": "http://twitter.com/acejinev/statuses/575397915285405696",
        "tco1_step1": "",
        "tco2_step1": "",
        "tco3_step1": ""
    },
    {
        "external_author_id": "2570250275",
        "author": "AIDEN7757",
        "content": "Guppy The Vampire Slayer. #FishTV",
        "region": "United States",
        "language": "English",
        "publish_date": "9/22/2016 9:16",
        "harvested_date": "9/22/2016 9:16",
        "following": "1631",
        "followers": "1459",
        "updates": "1966",
        "post_type": "",
        "account_type": "Hashtager",
        "retweet": "0",
        "account_category": "HashtagGamer",
        "new_june_2018": "0",
        "alt_external_id": "2570250275",
        "tweet_id": "778885709981777920",
        "article_url": "http://twitter.com/Aiden7757/statuses/778885709981777920",
        "tco1_step1": "",
        "tco2_step1": "",
        "tco3_step1": ""
    },
    {
        "external_author_id": "2878166306",
        "author": "ANDYHASHTAGGER",
        "content": "#TrumpsFavoriteHeadline Muslims recognize Trump as their prophet",
        "region": "United States",
        "language": "English",
        "publish_date": "8/17/2016 14:24",
        "harvested_date": "8/17/2016 14:24",
        "following": "20216",
        "followers": "23586",
        "updates": "13312",
        "post_type": "",
        "account_type": "Hashtager",
        "retweet": "0",
        "account_category": "HashtagGamer",
        "new_june_2018": "1",
        "alt_external_id": "2878166306",
        "tweet_id": "765917113500442628",
        "article_url": "http://twitter.com/AndyHashtagger/statuses/765917113500442628",
        "tco1_step1": "",
        "tco2_step1": "",
        "tco3_step1": ""
    },
    {
        "external_author_id": "2878166306",
        "author": "ANDYHASHTAGGER",
        "content": "#ReasonIAmDrunk Because I am capable of",
        "region": "United States",
        "language": "English",
        "publish_date": "10/18/2015 17:17",
        "harvested_date": "10/18/2015 17:19",
        "following": "12615",
        "followers": "15602",
        "updates": "3398",
        "post_type": "",
        "account_type": "Hashtager",
        "retweet": "0",
        "account_category": "HashtagGamer",
        "new_june_2018": "1",
        "alt_external_id": "2878166306",
        "tweet_id": "655794952429895680",
        "article_url": "http://twitter.com/AndyHashtagger/statuses/655794952429895680",
        "tco1_step1": "",
        "tco2_step1": "",
        "tco3_step1": ""
    },
    {
        "external_author_id": "895000000000000000",
        "author": "ANAAISLEC",
        "content": "RT 614swat: Remember that time when CNN sponsored a Trump assassination play then complained of a tweeter wrestling meme?",
        "region": "Unknown",
        "language": "English",
        "publish_date": "8/13/2017 21:37",
        "harvested_date": "8/13/2017 21:37",
        "following": "37",
        "followers": "49",
        "updates": "973",
        "post_type": "",
        "account_type": "Right",
        "retweet": "0",
        "account_category": "RightTroll",
        "new_june_2018": "0",
        "alt_external_id": "894801330912546817",
        "tweet_id": "896848132117590016",
        "article_url": "http://twitter.com/894801330912546817/statuses/896848132117590016",
        "tco1_step1": "",
        "tco2_step1": "",
        "tco3_step1": ""
    },
    {
        "external_author_id": "2616344667",
        "author": "AMANDAVGREEN",
        "content": "#GameShowHostPickUpLines \"100 people surveyed were asked, \"who's the hottest woman in this bar? And the survey SAID:      DING!  YOU!\"",
        "region": "United States",
        "language": "English",
        "publish_date": "9/5/2016 9:43",
        "harvested_date": "9/5/2016 9:44",
        "following": "2043",
        "followers": "2504",
        "updates": "3295",
        "post_type": "",
        "account_type": "Hashtager",
        "retweet": "0",
        "account_category": "HashtagGamer",
        "new_june_2018": "0",
        "alt_external_id": "2616344667",
        "tweet_id": "772731995956711424",
        "article_url": "http://twitter.com/AmandaVGreen/statuses/772731995956711424",
        "tco1_step1": "",
        "tco2_step1": "",
        "tco3_step1": ""
    },
    {
        "external_author_id": "893000000000000000",
        "author": "ALEXXDRTRR",
        "content": "RT mimirodgers46: tia6sc Just because this woman is black doesn't make one bit of difference. She needs to be locked up just like anyone el\u2026",
        "region": "Unknown",
        "language": "English",
        "publish_date": "8/18/2017 3:55",
        "harvested_date": "8/18/2017 3:55",
        "following": "34",
        "followers": "6",
        "updates": "2930",
        "post_type": "",
        "account_type": "Right",
        "retweet": "0",
        "account_category": "RightTroll",
        "new_june_2018": "0",
        "alt_external_id": "893397699579576321",
        "tweet_id": "898392902782550016",
        "article_url": "http://twitter.com/893397699579576321/statuses/898392902782550016",
        "tco1_step1": "",
        "tco2_step1": "",
        "tco3_step1": ""
    },
    {
        "external_author_id": "3312143142",
        "author": "4MYSQUAD",
        "content": "White folks \u2026 Always bring up race when it suits them not when it matters \u2014  Nate -HTGAWM",
        "region": "United States",
        "language": "English",
        "publish_date": "9/30/2015 13:56",
        "harvested_date": "9/30/2015 13:56",
        "following": "1918",
        "followers": "861",
        "updates": "3360",
        "post_type": "",
        "account_type": "Left",
        "retweet": "0",
        "account_category": "LeftTroll",
        "new_june_2018": "0",
        "alt_external_id": "3312143142",
        "tweet_id": "649221337869717504",
        "article_url": "http://twitter.com/4mysquad/statuses/649221337869717504",
        "tco1_step1": "",
        "tco2_step1": "",
        "tco3_step1": ""
    },
    {
        "external_author_id": "1529934134",
        "author": "ANN1EMCCONNELL",
        "content": "All yesterday night I wish I could dance twerk my ass #DumbGenieWishes",
        "region": "United States",
        "language": "English",
        "publish_date": "9/6/2015 16:26",
        "harvested_date": "9/6/2015 16:26",
        "following": "72",
        "followers": "62",
        "updates": "460",
        "post_type": "",
        "account_type": "Right",
        "retweet": "0",
        "account_category": "RightTroll",
        "new_june_2018": "1",
        "alt_external_id": "1529934134",
        "tweet_id": "640561778771001344",
        "article_url": "http://twitter.com/Ann1eMcconnell/statuses/640561778771001344",
        "tco1_step1": "",
        "tco2_step1": "",
        "tco3_step1": ""
    },
    {
        "external_author_id": "1649593796",
        "author": "ANN_HANAH",
        "content": "#StopIslam so you don't think ISIS will use this as an attempt to gain entry to the US? #IslamKills",
        "region": "United States",
        "language": "English",
        "publish_date": "3/22/2016 18:54",
        "harvested_date": "3/22/2016 18:54",
        "following": "56",
        "followers": "54",
        "updates": "456",
        "post_type": "",
        "account_type": "Right",
        "retweet": "0",
        "account_category": "RightTroll",
        "new_june_2018": "0",
        "alt_external_id": "1649593796",
        "tweet_id": "712351740431962116",
        "article_url": "http://twitter.com/Ann_HanAh/statuses/712351740431962116",
        "tco1_step1": "",
        "tco2_step1": "",
        "tco3_step1": ""
    },
    {
        "external_author_id": "891000000000000000",
        "author": "ARABMTR",
        "content": "RT jb19tele: FoxNews SscottSsmith84 JudicialWatch TheJusticeDept brookefoxnews Keep up the good work Judicial Watch!!",
        "region": "Unknown",
        "language": "English",
        "publish_date": "8/12/2017 7:57",
        "harvested_date": "8/12/2017 7:57",
        "following": "2949",
        "followers": "524",
        "updates": "1391",
        "post_type": "",
        "account_type": "Right",
        "retweet": "0",
        "account_category": "RightTroll",
        "new_june_2018": "0",
        "alt_external_id": "891230914629521408",
        "tweet_id": "896279453185298432",
        "article_url": "http://twitter.com/891230914629521408/statuses/896279453185298432",
        "tco1_step1": "",
        "tco2_step1": "",
        "tco3_step1": ""
    },
    {
        "external_author_id": "1875143624",
        "author": "AMIRAHPOPE",
        "content": "ABC News and rival GOP candidates unsuccessful in persuading Trump to   #ABCGOPDebate #ABCNews",
        "region": "United States",
        "language": "English",
        "publish_date": "2/7/2016 1:18",
        "harvested_date": "2/7/2016 1:19",
        "following": "87",
        "followers": "73",
        "updates": "12",
        "post_type": "",
        "account_type": "Left",
        "retweet": "0",
        "account_category": "LeftTroll",
        "new_june_2018": "0",
        "alt_external_id": "1875143624",
        "tweet_id": "696141068295745537",
        "article_url": "http://twitter.com/AmirahPope/statuses/696141068295745537",
        "tco1_step1": "",
        "tco2_step1": "",
        "tco3_step1": ""
    },
    {
        "external_author_id": "895000000000000000",
        "author": "AMIISTRS",
        "content": "RT PastorDScott: On Radio with seanhannity right now!",
        "region": "Unknown",
        "language": "English",
        "publish_date": "8/15/2017 22:05",
        "harvested_date": "8/15/2017 22:06",
        "following": "29",
        "followers": "4",
        "updates": "550",
        "post_type": "",
        "account_type": "Right",
        "retweet": "0",
        "account_category": "RightTroll",
        "new_june_2018": "0",
        "alt_external_id": "894792229809561600",
        "tweet_id": "897580089742942208",
        "article_url": "http://twitter.com/894792229809561600/statuses/897580089742942208",
        "tco1_step1": "",
        "tco2_step1": "",
        "tco3_step1": ""
    },
    {
        "external_author_id": "893000000000000000",
        "author": "ALEXXDRTRR",
        "content": "RT mitchellvii: I'm still waiting for someone,  anyone from the self-righteous perpetually outraged media to condemn #antifa or #blm violen\u2026",
        "region": "Unknown",
        "language": "English",
        "publish_date": "8/13/2017 18:47",
        "harvested_date": "8/13/2017 18:47",
        "following": "34",
        "followers": "7",
        "updates": "591",
        "post_type": "",
        "account_type": "Right",
        "retweet": "0",
        "account_category": "RightTroll",
        "new_june_2018": "0",
        "alt_external_id": "893397699579576321",
        "tweet_id": "896805404172333056",
        "article_url": "http://twitter.com/893397699579576321/statuses/896805404172333056",
        "tco1_step1": "",
        "tco2_step1": "",
        "tco3_step1": ""
    },
    {
        "external_author_id": "2534421182",
        "author": "ABIGAILSSILK",
        "content": "When my ex got engaged  #AndThatsWhenIStartedCrying",
        "region": "United States",
        "language": "English",
        "publish_date": "7/26/2016 8:26",
        "harvested_date": "7/26/2016 8:26",
        "following": "741",
        "followers": "498",
        "updates": "1248",
        "post_type": "",
        "account_type": "Hashtager",
        "retweet": "0",
        "account_category": "HashtagGamer",
        "new_june_2018": "0",
        "alt_external_id": "2534421182",
        "tweet_id": "757854596286906373",
        "article_url": "http://twitter.com/abigailssilk/statuses/757854596286906373",
        "tco1_step1": "",
        "tco2_step1": "",
        "tco3_step1": ""
    },
    {
        "external_author_id": "890000000000000000",
        "author": "AMBERLINETR",
        "content": "Peter_Fitz bugwannostra Look under a rock ? #amb",
        "region": "United States",
        "language": "English",
        "publish_date": "8/10/2017 22:25",
        "harvested_date": "8/10/2017 22:25",
        "following": "2941",
        "followers": "369",
        "updates": "1593",
        "post_type": "",
        "account_type": "Right",
        "retweet": "0",
        "account_category": "RightTroll",
        "new_june_2018": "0",
        "alt_external_id": "890429331373043712",
        "tweet_id": "895773106974928896",
        "article_url": "http://twitter.com/890429331373043712/statuses/895773106974928896",
        "tco1_step1": "",
        "tco2_step1": "",
        "tco3_step1": ""
    },
    {
        "external_author_id": "2616344667",
        "author": "AMANDAVGREEN",
        "content": "Harry to follow me.\"",
        "region": "United States",
        "language": "English",
        "publish_date": "11/24/2016 10:35",
        "harvested_date": "11/24/2016 10:35",
        "following": "3485",
        "followers": "3823",
        "updates": "4869",
        "post_type": "",
        "account_type": "Hashtager",
        "retweet": "0",
        "account_category": "HashtagGamer",
        "new_june_2018": "0",
        "alt_external_id": "2616344667",
        "tweet_id": "801735948425953280",
        "article_url": "http://twitter.com/2616344667/statuses/801735948425953280",
        "tco1_step1": "",
        "tco2_step1": "",
        "tco3_step1": ""
    },
    {
        "external_author_id": "3083086600",
        "author": "ALDRICH420",
        "content": "\"#Abaaoud and his whore cousin/girlfriend are dead.",
        "region": "United States",
        "language": "English",
        "publish_date": "3/22/2016 18:46",
        "harvested_date": "3/22/2016 18:46",
        "following": "963",
        "followers": "1053",
        "updates": "983",
        "post_type": "",
        "account_type": "Right",
        "retweet": "0",
        "account_category": "RightTroll",
        "new_june_2018": "0",
        "alt_external_id": "3083086600",
        "tweet_id": "712349741925838848",
        "article_url": "http://twitter.com/Aldrich420/statuses/712349741925838848",
        "tco1_step1": "",
        "tco2_step1": "",
        "tco3_step1": ""
    },
    {
        "external_author_id": "890000000000000000",
        "author": "AMBERLINETR",
        "content": "RT cheryl_kernot: NZ conspiracy strategy \"cooked up primarily by the Prime Minister and his deputy Julie Bishop\" say some Ministers\u2026 \u2026",
        "region": "United States",
        "language": "English",
        "publish_date": "8/18/2017 3:55",
        "harvested_date": "8/18/2017 3:55",
        "following": "3904",
        "followers": "549",
        "updates": "2970",
        "post_type": "",
        "account_type": "Right",
        "retweet": "0",
        "account_category": "RightTroll",
        "new_june_2018": "0",
        "alt_external_id": "890429331373043712",
        "tweet_id": "898392830741278720",
        "article_url": "http://twitter.com/890429331373043712/statuses/898392830741278720",
        "tco1_step1": "",
        "tco2_step1": "",
        "tco3_step1": ""
    },
    {
        "external_author_id": "895000000000000000",
        "author": "ANNAMINGT",
        "content": "RT LindaSuhler: I stand with my President against ALL political violence and ALL forms of bigotry and assumed 'superiority.'  WE ARE ALL AM\u2026",
        "region": "Unknown",
        "language": "English",
        "publish_date": "8/14/2017 15:50",
        "harvested_date": "8/14/2017 15:50",
        "following": "22",
        "followers": "2",
        "updates": "527",
        "post_type": "",
        "account_type": "Right",
        "retweet": "0",
        "account_category": "RightTroll",
        "new_june_2018": "0",
        "alt_external_id": "894837607061831681",
        "tweet_id": "897123349901529088",
        "article_url": "http://twitter.com/894837607061831681/statuses/897123349901529088",
        "tco1_step1": "",
        "tco2_step1": "",
        "tco3_step1": ""
    },
    {
        "external_author_id": "890000000000000000",
        "author": "AMBERLINETR",
        "content": "RT whitefangdragon: .Barnaby_Joyce Think you are smart enough to govern then you should have been smart enough to check you citizenship sta\u2026",
        "region": "United States",
        "language": "English",
        "publish_date": "8/14/2017 14:51",
        "harvested_date": "8/14/2017 14:51",
        "following": "2937",
        "followers": "367",
        "updates": "2182",
        "post_type": "",
        "account_type": "Right",
        "retweet": "0",
        "account_category": "RightTroll",
        "new_june_2018": "0",
        "alt_external_id": "890429331373043712",
        "tweet_id": "897108361703034880",
        "article_url": "http://twitter.com/890429331373043712/statuses/897108361703034880",
        "tco1_step1": "",
        "tco2_step1": "",
        "tco3_step1": ""
    },
    {
        "external_author_id": "1652987412",
        "author": "ALECMOOOOODY",
        "content": "Our govt will pay for everything! #WearHoodieForTrayvon",
        "region": "United States",
        "language": "English",
        "publish_date": "2/26/2016 13:47",
        "harvested_date": "2/26/2016 13:47",
        "following": "749",
        "followers": "228",
        "updates": "815",
        "post_type": "",
        "account_type": "Left",
        "retweet": "0",
        "account_category": "LeftTroll",
        "new_june_2018": "0",
        "alt_external_id": "1652987412",
        "tweet_id": "703214807349071872",
        "article_url": "http://twitter.com/AlecMooooody/statuses/703214807349071872",
        "tco1_step1": "",
        "tco2_step1": "",
        "tco3_step1": ""
    },
    {
        "external_author_id": "3072627228",
        "author": "ASSUNCAOWALLAS",
        "content": "chewing lips, I'm fed up with it, but can't stop",
        "region": "United States",
        "language": "English",
        "publish_date": "7/3/2015 11:41",
        "harvested_date": "7/3/2015 11:41",
        "following": "67",
        "followers": "58",
        "updates": "354",
        "post_type": "",
        "account_type": "Left",
        "retweet": "0",
        "account_category": "LeftTroll",
        "new_june_2018": "1",
        "alt_external_id": "3072627228",
        "tweet_id": "616934857634025472",
        "article_url": "http://twitter.com/assuncaowallas/statuses/616934857634025472",
        "tco1_step1": "",
        "tco2_step1": "",
        "tco3_step1": ""
    },
    {
        "external_author_id": "1657833811",
        "author": "ADRIENNE_GG",
        "content": "True Menstrual Blood #MakeTVSexy",
        "region": "United States",
        "language": "English",
        "publish_date": "8/23/2016 10:17",
        "harvested_date": "8/23/2016 10:19",
        "following": "734",
        "followers": "1014",
        "updates": "1381",
        "post_type": "",
        "account_type": "Hashtager",
        "retweet": "0",
        "account_category": "HashtagGamer",
        "new_june_2018": "0",
        "alt_external_id": "1657833811",
        "tweet_id": "768029493030105088",
        "article_url": "http://twitter.com/Adrienne_GG/statuses/768029493030105088",
        "tco1_step1": "",
        "tco2_step1": "",
        "tco3_step1": ""
    },
    {
        "external_author_id": "890000000000000000",
        "author": "AMBERLINETR",
        "content": "RT LennaLeprena: Icac finds that Eddie Obeid, Joe Tripodi and Tony Kelly engaged in corrupt Sinnerdinos sniggers into his champers. \u2026",
        "region": "United States",
        "language": "English",
        "publish_date": "8/3/2017 4:13",
        "harvested_date": "8/3/2017 4:13",
        "following": "2949",
        "followers": "276",
        "updates": "905",
        "post_type": "",
        "account_type": "Right",
        "retweet": "0",
        "account_category": "RightTroll",
        "new_june_2018": "0",
        "alt_external_id": "890429331373043712",
        "tweet_id": "892961548003627009",
        "article_url": "http://twitter.com/890429331373043712/statuses/892961548003627009",
        "tco1_step1": "",
        "tco2_step1": "",
        "tco3_step1": ""
    },
    {
        "external_author_id": "2570250275",
        "author": "AIDEN7757",
        "content": "#MentionSomeonePretty every person in this world is beautiful",
        "region": "United States",
        "language": "English",
        "publish_date": "3/16/2015 13:39",
        "harvested_date": "3/16/2015 13:39",
        "following": "260",
        "followers": "29",
        "updates": "597",
        "post_type": "",
        "account_type": "Hashtager",
        "retweet": "0",
        "account_category": "HashtagGamer",
        "new_june_2018": "0",
        "alt_external_id": "2570250275",
        "tweet_id": "577464087396769792",
        "article_url": "http://twitter.com/Aiden7757/statuses/577464087396769792",
        "tco1_step1": "",
        "tco2_step1": "",
        "tco3_step1": ""
    },
    {
        "external_author_id": "2612066397",
        "author": "ANDYDREWDANIELS",
        "content": "#ItsRiskyTo fight with strangers",
        "region": "United States",
        "language": "English",
        "publish_date": "1/25/2017 16:10",
        "harvested_date": "1/25/2017 16:11",
        "following": "2744",
        "followers": "2547",
        "updates": "2497",
        "post_type": "",
        "account_type": "Hashtager",
        "retweet": "0",
        "account_category": "HashtagGamer",
        "new_june_2018": "1",
        "alt_external_id": "2612066397",
        "tweet_id": "824288454511104002",
        "article_url": "http://twitter.com/2612066397/statuses/824288454511104002",
        "tco1_step1": "",
        "tco2_step1": "",
        "tco3_step1": ""
    },
    {
        "external_author_id": "895000000000000000",
        "author": "ANAAISLEC",
        "content": "RT kelleyh1961: pnehlen He's a slimeball... POTUS watch your back",
        "region": "Unknown",
        "language": "English",
        "publish_date": "8/14/2017 0:12",
        "harvested_date": "8/14/2017 0:12",
        "following": "37",
        "followers": "50",
        "updates": "995",
        "post_type": "",
        "account_type": "Right",
        "retweet": "0",
        "account_category": "RightTroll",
        "new_june_2018": "0",
        "alt_external_id": "894801330912546817",
        "tweet_id": "896887218597498881",
        "article_url": "http://twitter.com/894801330912546817/statuses/896887218597498881",
        "tco1_step1": "",
        "tco2_step1": "",
        "tco3_step1": ""
    },
    {
        "external_author_id": "2878166306",
        "author": "ANDYHASHTAGGER",
        "content": "#WithoutTheInternetI would get my sense of humor back to 'normal' and become another boring whiney tax payer",
        "region": "United States",
        "language": "English",
        "publish_date": "4/4/2016 13:08",
        "harvested_date": "4/4/2016 13:08",
        "following": "12252",
        "followers": "19470",
        "updates": "6769",
        "post_type": "",
        "account_type": "Hashtager",
        "retweet": "0",
        "account_category": "HashtagGamer",
        "new_june_2018": "1",
        "alt_external_id": "2878166306",
        "tweet_id": "716975712914116608",
        "article_url": "http://twitter.com/AndyHashtagger/statuses/716975712914116608",
        "tco1_step1": "",
        "tco2_step1": "",
        "tco3_step1": ""
    },
    {
        "external_author_id": "2616344667",
        "author": "AMANDAVGREEN",
        "content": "#IKnewWeWereDoomed when I first learned what was legal under campaign finance laws.",
        "region": "United States",
        "language": "English",
        "publish_date": "1/24/2017 10:04",
        "harvested_date": "1/24/2017 10:05",
        "following": "4549",
        "followers": "5397",
        "updates": "5947",
        "post_type": "",
        "account_type": "Hashtager",
        "retweet": "0",
        "account_category": "HashtagGamer",
        "new_june_2018": "0",
        "alt_external_id": "2616344667",
        "tweet_id": "823833956344889344",
        "article_url": "http://twitter.com/2616344667/statuses/823833956344889344",
        "tco1_step1": "",
        "tco2_step1": "",
        "tco3_step1": ""
    },
    {
        "external_author_id": "2614742415",
        "author": "ANDREWHEDDD",
        "content": "#VegasGOPDebate Have you heard #BenCarson talking about Pyramids were used to store grain? And he wants to be our president! #GOPDebate",
        "region": "United States",
        "language": "English",
        "publish_date": "12/16/2015 3:10",
        "harvested_date": "12/16/2015 3:11",
        "following": "54",
        "followers": "7",
        "updates": "22",
        "post_type": "",
        "account_type": "Right",
        "retweet": "0",
        "account_category": "RightTroll",
        "new_june_2018": "0",
        "alt_external_id": "2614742415",
        "tweet_id": "676962682675830784",
        "article_url": "http://twitter.com/AndrewHeddd/statuses/676962682675830784",
        "tco1_step1": "",
        "tco2_step1": "",
        "tco3_step1": ""
    },
    {
        "external_author_id": "893000000000000000",
        "author": "ALAXXATR",
        "content": "RT realDonaldTrump: Study what General Pershing of the United States did to terrorists when caught. There was no more Radical Islamic Terro\u2026",
        "region": "Unknown",
        "language": "English",
        "publish_date": "8/17/2017 18:54",
        "harvested_date": "8/17/2017 18:54",
        "following": "28",
        "followers": "2",
        "updates": "720",
        "post_type": "",
        "account_type": "Right",
        "retweet": "0",
        "account_category": "RightTroll",
        "new_june_2018": "0",
        "alt_external_id": "893396485555048448",
        "tweet_id": "898256797957574657",
        "article_url": "http://twitter.com/893396485555048448/statuses/898256797957574657",
        "tco1_step1": "",
        "tco2_step1": "",
        "tco3_step1": ""
    },
    {
        "external_author_id": "1657833811",
        "author": "ADRIENNE_GG",
        "content": "Kiss me, and you will see how important I am",
        "region": "United States",
        "language": "English",
        "publish_date": "2/16/2015 14:00",
        "harvested_date": "2/16/2015 14:02",
        "following": "108",
        "followers": "129",
        "updates": "376",
        "post_type": "",
        "account_type": "Hashtager",
        "retweet": "0",
        "account_category": "HashtagGamer",
        "new_june_2018": "0",
        "alt_external_id": "1657833811",
        "tweet_id": "567322603279237120",
        "article_url": "http://twitter.com/Adrienne_GG/statuses/567322603279237120",
        "tco1_step1": "",
        "tco2_step1": "",
        "tco3_step1": ""
    },
    {
        "external_author_id": "891000000000000000",
        "author": "AFEELIUTR",
        "content": "#adee RT Pink_About_it: You know media is corrupt to the core when #awanBrothers scandal tops national security &amp; the biggest lie of the ce\u2026",
        "region": "United States",
        "language": "English",
        "publish_date": "7/30/2017 23:26",
        "harvested_date": "7/30/2017 23:26",
        "following": "994",
        "followers": "328",
        "updates": "501",
        "post_type": "",
        "account_type": "Right",
        "retweet": "0",
        "account_category": "RightTroll",
        "new_june_2018": "0",
        "alt_external_id": "891183122305486848",
        "tweet_id": "891802225873477632",
        "article_url": "http://twitter.com/891183122305486848/statuses/891802225873477632",
        "tco1_step1": "",
        "tco2_step1": "",
        "tco3_step1": ""
    },
    {
        "external_author_id": "890000000000000000",
        "author": "AMBERLINETR",
        "content": "RT samdastyari: The Senate has become a circus. Hanson is a disgrace. Government is weak and reliant on her vote. Pathetic. #amb",
        "region": "United States",
        "language": "English",
        "publish_date": "8/18/2017 0:10",
        "harvested_date": "8/18/2017 0:10",
        "following": "3904",
        "followers": "534",
        "updates": "2931",
        "post_type": "",
        "account_type": "Right",
        "retweet": "0",
        "account_category": "RightTroll",
        "new_june_2018": "0",
        "alt_external_id": "890429331373043712",
        "tweet_id": "898336189437968384",
        "article_url": "http://twitter.com/890429331373043712/statuses/898336189437968384",
        "tco1_step1": "",
        "tco2_step1": "",
        "tco3_step1": ""
    },
    {
        "external_author_id": "895000000000000000",
        "author": "ANGELISTRR",
        "content": "RT RealMattCouch: It's amazing how people can start a Go Fund Me to buy a Potato Gun, but America First gets shut down for investigating mu\u2026",
        "region": "Unknown",
        "language": "English",
        "publish_date": "8/11/2017 17:46",
        "harvested_date": "8/11/2017 17:46",
        "following": "49",
        "followers": "5",
        "updates": "76",
        "post_type": "",
        "account_type": "Right",
        "retweet": "0",
        "account_category": "RightTroll",
        "new_june_2018": "0",
        "alt_external_id": "894820555421089793",
        "tweet_id": "896065189476302848",
        "article_url": "http://twitter.com/894820555421089793/statuses/896065189476302848",
        "tco1_step1": "",
        "tco2_step1": "",
        "tco3_step1": ""
    },
    {
        "external_author_id": "895000000000000000",
        "author": "AMYYSLEGENTR",
        "content": "DWStweets Car driver was part of #resist....what say you now?",
        "region": "Unknown",
        "language": "English",
        "publish_date": "8/12/2017 23:42",
        "harvested_date": "8/12/2017 23:42",
        "following": "26",
        "followers": "6",
        "updates": "339",
        "post_type": "",
        "account_type": "Right",
        "retweet": "0",
        "account_category": "RightTroll",
        "new_june_2018": "0",
        "alt_external_id": "894794223207161856",
        "tweet_id": "896517237757976576",
        "article_url": "http://twitter.com/894794223207161856/statuses/896517237757976576",
        "tco1_step1": "",
        "tco2_step1": "",
        "tco3_step1": ""
    },
    {
        "external_author_id": "890000000000000000",
        "author": "AMBERLINETR",
        "content": "RT fqxjv: ObamneyCare leaves 28 M people, many just like Timmy, behind altogether. Improved, universal #MedicareForAll would\u2026 \u2026",
        "region": "United States",
        "language": "English",
        "publish_date": "7/27/2017 5:20",
        "harvested_date": "7/27/2017 5:20",
        "following": "964",
        "followers": "0",
        "updates": "11",
        "post_type": "",
        "account_type": "Right",
        "retweet": "0",
        "account_category": "RightTroll",
        "new_june_2018": "0",
        "alt_external_id": "890429331373043712",
        "tweet_id": "890441687759192064",
        "article_url": "http://twitter.com/890429331373043712/statuses/890441687759192064",
        "tco1_step1": "",
        "tco2_step1": "",
        "tco3_step1": ""
    },
    {
        "external_author_id": "3083086600",
        "author": "ALDRICH420",
        "content": "#DEMDebate America will always remember hillary",
        "region": "United States",
        "language": "English",
        "publish_date": "3/10/2016 1:44",
        "harvested_date": "3/10/2016 1:44",
        "following": "703",
        "followers": "915",
        "updates": "888",
        "post_type": "",
        "account_type": "Right",
        "retweet": "0",
        "account_category": "RightTroll",
        "new_june_2018": "0",
        "alt_external_id": "3083086600",
        "tweet_id": "707743870063407105",
        "article_url": "http://twitter.com/Aldrich420/statuses/707743870063407105",
        "tco1_step1": "",
        "tco2_step1": "",
        "tco3_step1": ""
    },
    {
        "external_author_id": "893000000000000000",
        "author": "ALEXXDRTRR",
        "content": "RT realDonaldTrump: MAKE AMERICA GREAT AGAIN!",
        "region": "Unknown",
        "language": "English",
        "publish_date": "8/12/2017 0:55",
        "harvested_date": "8/12/2017 0:56",
        "following": "34",
        "followers": "6",
        "updates": "306",
        "post_type": "",
        "account_type": "Right",
        "retweet": "0",
        "account_category": "RightTroll",
        "new_june_2018": "0",
        "alt_external_id": "893397699579576321",
        "tweet_id": "896173237285138432",
        "article_url": "http://twitter.com/893397699579576321/statuses/896173237285138432",
        "tco1_step1": "",
        "tco2_step1": "",
        "tco3_step1": ""
    },
    {
        "external_author_id": "1580700565",
        "author": "ARNOLDPARRK",
        "content": "Turn on to politics, or politics will turn on you.",
        "region": "United States",
        "language": "English",
        "publish_date": "11/26/2015 13:04",
        "harvested_date": "11/26/2015 13:05",
        "following": "53",
        "followers": "50",
        "updates": "317",
        "post_type": "",
        "account_type": "Koch",
        "retweet": "0",
        "account_category": "Fearmonger",
        "new_june_2018": "0",
        "alt_external_id": "1580700565",
        "tweet_id": "669864351784951809",
        "article_url": "http://twitter.com/arnoldparrk/statuses/669864351784951809",
        "tco1_step1": "",
        "tco2_step1": "",
        "tco3_step1": ""
    },
    {
        "external_author_id": "895000000000000000",
        "author": "ANNAMINGT",
        "content": "RT terrymendozer: Now they are back to targeting Bannon (again) Remember what he said You wouldn't think they would give us back our countr\u2026",
        "region": "Unknown",
        "language": "English",
        "publish_date": "8/15/2017 19:50",
        "harvested_date": "8/15/2017 19:50",
        "following": "22",
        "followers": "1",
        "updates": "772",
        "post_type": "",
        "account_type": "Right",
        "retweet": "0",
        "account_category": "RightTroll",
        "new_june_2018": "0",
        "alt_external_id": "894837607061831681",
        "tweet_id": "897546054601670656",
        "article_url": "http://twitter.com/894837607061831681/statuses/897546054601670656",
        "tco1_step1": "",
        "tco2_step1": "",
        "tco3_step1": ""
    },
    {
        "external_author_id": "895000000000000000",
        "author": "AMBERRPAR",
        "content": "RT TomiLahren: Wouldn't it be nice if the networks condemning white supremacists would also condemn the Alt Left and ANTIFA terrorists? One\u2026",
        "region": "Unknown",
        "language": "English",
        "publish_date": "8/17/2017 11:54",
        "harvested_date": "8/17/2017 11:54",
        "following": "1013",
        "followers": "107",
        "updates": "1025",
        "post_type": "",
        "account_type": "Right",
        "retweet": "0",
        "account_category": "RightTroll",
        "new_june_2018": "0",
        "alt_external_id": "894787222964101120",
        "tweet_id": "898151029518344193",
        "article_url": "http://twitter.com/894787222964101120/statuses/898151029518344193",
        "tco1_step1": "",
        "tco2_step1": "",
        "tco3_step1": ""
    },
    {
        "external_author_id": "2612066397",
        "author": "ANDYDREWDANIELS",
        "content": "#WhatIWouldTellA15YearOldMe wash that vile hair gel out right now",
        "region": "United States",
        "language": "English",
        "publish_date": "1/14/2017 11:26",
        "harvested_date": "1/14/2017 11:26",
        "following": "2364",
        "followers": "2272",
        "updates": "2328",
        "post_type": "",
        "account_type": "Hashtager",
        "retweet": "0",
        "account_category": "HashtagGamer",
        "new_june_2018": "1",
        "alt_external_id": "2612066397",
        "tweet_id": "820230499830480896",
        "article_url": "http://twitter.com/2612066397/statuses/820230499830480896",
        "tco1_step1": "",
        "tco2_step1": "",
        "tco3_step1": ""
    },
    {
        "external_author_id": "2570250275",
        "author": "AIDEN7757",
        "content": "#SecondHandGifts  A toothbrush",
        "region": "United States",
        "language": "English",
        "publish_date": "12/21/2016 16:20",
        "harvested_date": "12/21/2016 16:21",
        "following": "2677",
        "followers": "2610",
        "updates": "3198",
        "post_type": "",
        "account_type": "Hashtager",
        "retweet": "0",
        "account_category": "HashtagGamer",
        "new_june_2018": "0",
        "alt_external_id": "2570250275",
        "tweet_id": "811607395742924802",
        "article_url": "http://twitter.com/2570250275/statuses/811607395742924802",
        "tco1_step1": "",
        "tco2_step1": "",
        "tco3_step1": ""
    },
    {
        "external_author_id": "2534421182",
        "author": "ABIGAILSSILK",
        "content": "#singlebecause I`m in search of a prince!",
        "region": "United States",
        "language": "English",
        "publish_date": "3/18/2015 7:33",
        "harvested_date": "3/18/2015 7:33",
        "following": "186",
        "followers": "134",
        "updates": "832",
        "post_type": "",
        "account_type": "Hashtager",
        "retweet": "0",
        "account_category": "HashtagGamer",
        "new_june_2018": "0",
        "alt_external_id": "2534421182",
        "tweet_id": "578096919068594177",
        "article_url": "http://twitter.com/abigailssilk/statuses/578096919068594177",
        "tco1_step1": "",
        "tco2_step1": "",
        "tco3_step1": ""
    },
    {
        "external_author_id": "890000000000000000",
        "author": "AMBERLINETR",
        "content": "LesStonehouse AlboMP political_alert Yes and tsunamis #amb",
        "region": "United States",
        "language": "English",
        "publish_date": "8/16/2017 5:46",
        "harvested_date": "8/16/2017 5:46",
        "following": "3904",
        "followers": "369",
        "updates": "2444",
        "post_type": "",
        "account_type": "Right",
        "retweet": "0",
        "account_category": "RightTroll",
        "new_june_2018": "0",
        "alt_external_id": "890429331373043712",
        "tweet_id": "897695959605538816",
        "article_url": "http://twitter.com/890429331373043712/statuses/897695959605538816",
        "tco1_step1": "",
        "tco2_step1": "",
        "tco3_step1": ""
    },
    {
        "external_author_id": "1654782062",
        "author": "ADRI_LOW_R",
        "content": "Im following back today so follow for follow back",
        "region": "United States",
        "language": "English",
        "publish_date": "7/4/2015 9:56",
        "harvested_date": "7/4/2015 9:56",
        "following": "51",
        "followers": "68",
        "updates": "414",
        "post_type": "",
        "account_type": "Left",
        "retweet": "0",
        "account_category": "LeftTroll",
        "new_june_2018": "0",
        "alt_external_id": "1654782062",
        "tweet_id": "617270658620219392",
        "article_url": "http://twitter.com/Adri_Low_r/statuses/617270658620219392",
        "tco1_step1": "",
        "tco2_step1": "",
        "tco3_step1": ""
    },
    {
        "external_author_id": "890000000000000000",
        "author": "AMBERLINETR",
        "content": "RT Mumdeep: MrPinkCarpet vanbadham MikeCarlton01 Comments now on my fb friend (Lib member, mackellar) from their other Lib (\u2026 \u2026",
        "region": "United States",
        "language": "English",
        "publish_date": "8/12/2017 11:38",
        "harvested_date": "8/12/2017 11:38",
        "following": "2940",
        "followers": "370",
        "updates": "1812",
        "post_type": "",
        "account_type": "Right",
        "retweet": "0",
        "account_category": "RightTroll",
        "new_june_2018": "0",
        "alt_external_id": "890429331373043712",
        "tweet_id": "896335057861967872",
        "article_url": "http://twitter.com/890429331373043712/statuses/896335057861967872",
        "tco1_step1": "",
        "tco2_step1": "",
        "tco3_step1": ""
    },
    {
        "external_author_id": "893000000000000000",
        "author": "ALANISSTRS",
        "content": "RT DLoesch: When can I expect to be arrested, RepKathleenRice ? Do you have enough secret security to take millions of members into custody\u2026",
        "region": "Unknown",
        "language": "English",
        "publish_date": "8/12/2017 0:36",
        "harvested_date": "8/12/2017 0:36",
        "following": "9",
        "followers": "4",
        "updates": "412",
        "post_type": "",
        "account_type": "Right",
        "retweet": "0",
        "account_category": "RightTroll",
        "new_june_2018": "0",
        "alt_external_id": "893391276942426112",
        "tweet_id": "896168567242203140",
        "article_url": "http://twitter.com/893391276942426112/statuses/896168567242203140",
        "tco1_step1": "",
        "tco2_step1": "",
        "tco3_step1": ""
    },
    {
        "external_author_id": "1657833811",
        "author": "ADRIENNE_GG",
        "content": "Life is not the way it is supposed to be. It is the way it is. The way you cope with it is what makes the difference.",
        "region": "United States",
        "language": "English",
        "publish_date": "3/18/2015 9:10",
        "harvested_date": "3/18/2015 9:10",
        "following": "150",
        "followers": "147",
        "updates": "799",
        "post_type": "",
        "account_type": "Hashtager",
        "retweet": "0",
        "account_category": "HashtagGamer",
        "new_june_2018": "0",
        "alt_external_id": "1657833811",
        "tweet_id": "578121353481465857",
        "article_url": "http://twitter.com/Adrienne_GG/statuses/578121353481465857",
        "tco1_step1": "",
        "tco2_step1": "",
        "tco3_step1": ""
    },
    {
        "external_author_id": "2878166306",
        "author": "ANDYHASHTAGGER",
        "content": "#MyMondayStartsWith a cup of strong coffee",
        "region": "United States",
        "language": "English",
        "publish_date": "11/30/2015 14:04",
        "harvested_date": "11/30/2015 14:04",
        "following": "16318",
        "followers": "17152",
        "updates": "4128",
        "post_type": "",
        "account_type": "Hashtager",
        "retweet": "0",
        "account_category": "HashtagGamer",
        "new_june_2018": "1",
        "alt_external_id": "2878166306",
        "tweet_id": "671329009280679936",
        "article_url": "http://twitter.com/AndyHashtagger/statuses/671329009280679936",
        "tco1_step1": "",
        "tco2_step1": "",
        "tco3_step1": ""
    },
    {
        "external_author_id": "895000000000000000",
        "author": "ASWWIMMORRIS",
        "content": "LtStevenLRogers veritaz realDonaldTrump Right on brother! Cry baby cry!",
        "region": "Unknown",
        "language": "English",
        "publish_date": "8/15/2017 5:23",
        "harvested_date": "8/15/2017 5:23",
        "following": "0",
        "followers": "1",
        "updates": "486",
        "post_type": "",
        "account_type": "Right",
        "retweet": "0",
        "account_category": "RightTroll",
        "new_june_2018": "0",
        "alt_external_id": "895224264424648704",
        "tweet_id": "897327821420474368",
        "article_url": "http://twitter.com/895224264424648704/statuses/897327821420474368",
        "tco1_step1": "",
        "tco2_step1": "",
        "tco3_step1": ""
    },
    {
        "external_author_id": "3075888895",
        "author": "ALTMANBELINDA",
        "content": "#TrumpBecause Americans are tired of what goes on in Washington. WE WANT REAL CHANGES #Trump2016 #MakeAmericaGreatAgain \ufffd\ufffd\ufffd",
        "region": "United States",
        "language": "English",
        "publish_date": "8/13/2015 16:10",
        "harvested_date": "8/13/2015 16:10",
        "following": "50",
        "followers": "60",
        "updates": "410",
        "post_type": "",
        "account_type": "Right",
        "retweet": "0",
        "account_category": "RightTroll",
        "new_june_2018": "0",
        "alt_external_id": "3075888895",
        "tweet_id": "631860281593884672",
        "article_url": "http://twitter.com/AltmanBelinda/statuses/631860281593884672",
        "tco1_step1": "",
        "tco2_step1": "",
        "tco3_step1": ""
    },
    {
        "external_author_id": "2878166306",
        "author": "ANDYHASHTAGGER",
        "content": "#MyNewYearStartedWith hopes about better president this year",
        "region": "United States",
        "language": "English",
        "publish_date": "1/4/2016 14:42",
        "harvested_date": "1/4/2016 14:42",
        "following": "17231",
        "followers": "17704",
        "updates": "5120",
        "post_type": "",
        "account_type": "Hashtager",
        "retweet": "0",
        "account_category": "HashtagGamer",
        "new_june_2018": "1",
        "alt_external_id": "2878166306",
        "tweet_id": "684022159384166400",
        "article_url": "http://twitter.com/AndyHashtagger/statuses/684022159384166400",
        "tco1_step1": "",
        "tco2_step1": "",
        "tco3_step1": ""
    },
    {
        "external_author_id": "1529934134",
        "author": "ANN1EMCCONNELL",
        "content": "We have to stop this circuis and we mustn\u2019t let Trump become the president #VegasGOPDebate",
        "region": "United States",
        "language": "English",
        "publish_date": "12/16/2015 1:29",
        "harvested_date": "12/16/2015 1:29",
        "following": "72",
        "followers": "62",
        "updates": "35",
        "post_type": "",
        "account_type": "Right",
        "retweet": "0",
        "account_category": "RightTroll",
        "new_june_2018": "1",
        "alt_external_id": "1529934134",
        "tweet_id": "676937060859662336",
        "article_url": "http://twitter.com/Ann1eMcconnell/statuses/676937060859662336",
        "tco1_step1": "",
        "tco2_step1": "",
        "tco3_step1": ""
    },
    {
        "external_author_id": "2570250275",
        "author": "AIDEN7757",
        "content": "Respect women, I don't care if they a 2 or a 10 we don't beat on Kat Stacks, we just bring it to an end  \u2013 The Game",
        "region": "United States",
        "language": "English",
        "publish_date": "1/11/2015 14:09",
        "harvested_date": "1/11/2015 14:09",
        "following": "0",
        "followers": "0",
        "updates": "39",
        "post_type": "",
        "account_type": "Hashtager",
        "retweet": "0",
        "account_category": "HashtagGamer",
        "new_june_2018": "0",
        "alt_external_id": "2570250275",
        "tweet_id": "554278839480635392",
        "article_url": "http://twitter.com/Aiden7757/statuses/554278839480635392",
        "tco1_step1": "",
        "tco2_step1": "",
        "tco3_step1": ""
    },
    {
        "external_author_id": "2616344667",
        "author": "AMANDAVGREEN",
        "content": "Study o chem on your phone #ThingsToDoInAWaitingRoom #UseYourTimeWisely #NoProcrastination",
        "region": "United States",
        "language": "English",
        "publish_date": "8/4/2016 9:40",
        "harvested_date": "8/4/2016 9:40",
        "following": "2392",
        "followers": "1962",
        "updates": "2713",
        "post_type": "",
        "account_type": "Hashtager",
        "retweet": "0",
        "account_category": "HashtagGamer",
        "new_june_2018": "0",
        "alt_external_id": "2616344667",
        "tweet_id": "761134714220535808",
        "article_url": "http://twitter.com/AmandaVGreen/statuses/761134714220535808",
        "tco1_step1": "",
        "tco2_step1": "",
        "tco3_step1": ""
    },
    {
        "external_author_id": "3075888895",
        "author": "ALTMANBELINDA",
        "content": "#GOPDebate #StopTheGOP Trumpageddon IowaDebate!",
        "region": "United States",
        "language": "English",
        "publish_date": "1/29/2016 3:14",
        "harvested_date": "1/29/2016 3:15",
        "following": "50",
        "followers": "60",
        "updates": "79",
        "post_type": "",
        "account_type": "Right",
        "retweet": "0",
        "account_category": "RightTroll",
        "new_june_2018": "0",
        "alt_external_id": "3075888895",
        "tweet_id": "692908748990500869",
        "article_url": "http://twitter.com/AltmanBelinda/statuses/692908748990500869",
        "tco1_step1": "",
        "tco2_step1": "",
        "tco3_step1": ""
    },
    {
        "external_author_id": "893000000000000000",
        "author": "ALEXXDRTRR",
        "content": "theTrumpSpring Oh man..... they look miserably despicable...after 8 years I hope their face don't get stuck in the hateful look",
        "region": "Unknown",
        "language": "English",
        "publish_date": "8/13/2017 19:19",
        "harvested_date": "8/13/2017 19:19",
        "following": "34",
        "followers": "7",
        "updates": "614",
        "post_type": "",
        "account_type": "Right",
        "retweet": "0",
        "account_category": "RightTroll",
        "new_june_2018": "0",
        "alt_external_id": "893397699579576321",
        "tweet_id": "896813407403421697",
        "article_url": "http://twitter.com/893397699579576321/statuses/896813407403421697",
        "tco1_step1": "",
        "tco2_step1": "",
        "tco3_step1": ""
    },
    {
        "external_author_id": "890000000000000000",
        "author": "AMBERLINETR",
        "content": "RT Kon__K: Number of people killed by terrorism since 1981 in Australia:  4  Number of women killed by male violence since the 11th of July\u2026",
        "region": "United States",
        "language": "English",
        "publish_date": "8/18/2017 6:20",
        "harvested_date": "8/18/2017 6:20",
        "following": "3904",
        "followers": "553",
        "updates": "3032",
        "post_type": "",
        "account_type": "Right",
        "retweet": "0",
        "account_category": "RightTroll",
        "new_june_2018": "0",
        "alt_external_id": "890429331373043712",
        "tweet_id": "898429455990784000",
        "article_url": "http://twitter.com/890429331373043712/statuses/898429455990784000",
        "tco1_step1": "",
        "tco2_step1": "",
        "tco3_step1": ""
    },
    {
        "external_author_id": "1660099243",
        "author": "ADELE_BROCK",
        "content": "Champions have the courage to keep turning the pages because they know a better chapter lies ahead.  \u2013 Paula White",
        "region": "United States",
        "language": "English",
        "publish_date": "7/3/2015 11:32",
        "harvested_date": "7/3/2015 11:32",
        "following": "53",
        "followers": "59",
        "updates": "357",
        "post_type": "",
        "account_type": "Right",
        "retweet": "0",
        "account_category": "RightTroll",
        "new_june_2018": "1",
        "alt_external_id": "1660099243",
        "tweet_id": "616932563848826881",
        "article_url": "http://twitter.com/adele_brock/statuses/616932563848826881",
        "tco1_step1": "",
        "tco2_step1": "",
        "tco3_step1": ""
    },
    {
        "external_author_id": "893000000000000000",
        "author": "ALANISSTRS",
        "content": "RT oliverdarcy: Trump is asked if he thinks Mike Pence will be a candidate for president in 2020: \"I don't think so\"",
        "region": "Unknown",
        "language": "English",
        "publish_date": "8/11/2017 22:36",
        "harvested_date": "8/11/2017 22:36",
        "following": "9",
        "followers": "4",
        "updates": "308",
        "post_type": "",
        "account_type": "Right",
        "retweet": "0",
        "account_category": "RightTroll",
        "new_june_2018": "0",
        "alt_external_id": "893391276942426112",
        "tweet_id": "896138252763119616",
        "article_url": "http://twitter.com/893391276942426112/statuses/896138252763119616",
        "tco1_step1": "",
        "tco2_step1": "",
        "tco3_step1": ""
    },
    {
        "external_author_id": "2753257234",
        "author": "ARONHOLDEN8",
        "content": "\"The most well-versed candidate in bankruptcy proceedings.\" #TrumpCampaignSlogans",
        "region": "United States",
        "language": "English",
        "publish_date": "7/25/2015 14:07",
        "harvested_date": "7/25/2015 14:07",
        "following": "135",
        "followers": "77",
        "updates": "945",
        "post_type": "",
        "account_type": "Hashtager",
        "retweet": "0",
        "account_category": "HashtagGamer",
        "new_june_2018": "1",
        "alt_external_id": "2753257234",
        "tweet_id": "624943964873990145",
        "article_url": "http://twitter.com/AronHolden8/statuses/624943964873990145",
        "tco1_step1": "",
        "tco2_step1": "",
        "tco3_step1": ""
    },
    {
        "external_author_id": "2878166306",
        "author": "ANDYHASHTAGGER",
        "content": "#SuperheroWeDeserve would host a hashtag game everytime he would be out to kick some bad guy's ass",
        "region": "United States",
        "language": "English",
        "publish_date": "3/7/2016 14:22",
        "harvested_date": "3/7/2016 14:22",
        "following": "14429",
        "followers": "18907",
        "updates": "6134",
        "post_type": "",
        "account_type": "Hashtager",
        "retweet": "0",
        "account_category": "HashtagGamer",
        "new_june_2018": "1",
        "alt_external_id": "2878166306",
        "tweet_id": "706847436216672256",
        "article_url": "http://twitter.com/AndyHashtagger/statuses/706847436216672256",
        "tco1_step1": "",
        "tco2_step1": "",
        "tco3_step1": ""
    },
    {
        "external_author_id": "1657833811",
        "author": "ADRIENNE_GG",
        "content": "A Bible Called Quest  #MakeMusicReligious",
        "region": "United States",
        "language": "English",
        "publish_date": "12/18/2016 13:25",
        "harvested_date": "12/18/2016 13:25",
        "following": "2453",
        "followers": "2885",
        "updates": "2973",
        "post_type": "",
        "account_type": "Hashtager",
        "retweet": "0",
        "account_category": "HashtagGamer",
        "new_june_2018": "0",
        "alt_external_id": "1657833811",
        "tweet_id": "810476045245837312",
        "article_url": "http://twitter.com/1657833811/statuses/810476045245837312",
        "tco1_step1": "",
        "tco2_step1": "",
        "tco3_step1": ""
    },
    {
        "external_author_id": "895000000000000000",
        "author": "AMYYSLEGENTR",
        "content": "OCNaNa2013 ProPublica Im no nazi but i believe in freedom of speech to all. One side had a legal permit, the antifa never do.",
        "region": "Unknown",
        "language": "English",
        "publish_date": "8/15/2017 14:20",
        "harvested_date": "8/15/2017 14:21",
        "following": "26",
        "followers": "5",
        "updates": "764",
        "post_type": "",
        "account_type": "Right",
        "retweet": "0",
        "account_category": "RightTroll",
        "new_june_2018": "0",
        "alt_external_id": "894794223207161856",
        "tweet_id": "897463003112755201",
        "article_url": "http://twitter.com/894794223207161856/statuses/897463003112755201",
        "tco1_step1": "",
        "tco2_step1": "",
        "tco3_step1": ""
    },
    {
        "external_author_id": "1670762347",
        "author": "ADAMCHAPMANJR",
        "content": "Please let her and her child be safe  #BlackSkinIsNotACrime #PhilandoCastile",
        "region": "United States",
        "language": "English",
        "publish_date": "7/7/2016 15:03",
        "harvested_date": "7/7/2016 15:03",
        "following": "1008",
        "followers": "710",
        "updates": "1219",
        "post_type": "",
        "account_type": "Left",
        "retweet": "0",
        "account_category": "LeftTroll",
        "new_june_2018": "0",
        "alt_external_id": "1670762347",
        "tweet_id": "751069012512104449",
        "article_url": "http://twitter.com/AdamChapmanJR/statuses/751069012512104449",
        "tco1_step1": "",
        "tco2_step1": "",
        "tco3_step1": ""
    },
    {
        "external_author_id": "895000000000000000",
        "author": "ANIIANTRS",
        "content": "RT sean_spicier: I fail to see how removing all these statues will get your lazy ass off the couch and get a job",
        "region": "Unknown",
        "language": "English",
        "publish_date": "8/19/2017 14:20",
        "harvested_date": "8/19/2017 14:20",
        "following": "1028",
        "followers": "142",
        "updates": "2446",
        "post_type": "",
        "account_type": "Right",
        "retweet": "0",
        "account_category": "RightTroll",
        "new_june_2018": "0",
        "alt_external_id": "894845726840283136",
        "tweet_id": "898912550968012800",
        "article_url": "http://twitter.com/894845726840283136/statuses/898912550968012800",
        "tco1_step1": "",
        "tco2_step1": "",
        "tco3_step1": ""
    }
]