[[]{"id": 1255282109733900289, "conversation_id": "1247611743301439489", "created_at": "2020-04-28 19:45:51 EDT", "date": "2020-04-28", "time": "19:45:51", "timezone": "-0500", "user_id": 787377634523086848, "username": "waltkostrzewski", "name": "Walt Kostrzewski", "place": "", "tweet": "@RyanMacDonnell @DonJuan28001653 @gtconway3d Election security...recall very onerous items but not specifics...want reform...let’s start with IDs then let’s talk what else needs to change...what else...by the way last pic is what social programs should always do!  https://t.co/EI3SfLBwCv", "language": "en", "mentions": [], "urls": [], "photos": ["https://pbs.twimg.com/media/EWuobInX0AEoPZ6.jpg", "https://pbs.twimg.com/media/EWuobInXQAIxmAM.jpg", "https://pbs.twimg.com/media/EWuobIpX0AA-Cb_.jpg", "https://pbs.twimg.com/media/EWuobIoWkAkhj8E.jpg"], "replies_count": 0, "retweets_count": 0, "likes_count": 0, "hashtags": [], "cashtags": [], "link": "https://twitter.com/WaltKostrzewski/status/1255282109733900289", "retweet": false, "quote_url": "", "video": 1, "thumbnail": "https://pbs.twimg.com/media/EWuobInX0AEoPZ6.jpg", "near": "", "geo": "", "source": "", "user_rt_id": "", "user_rt": "", "retweet_id": "", "reply_to": [{"screen_name": "RyanMacDonnell", "name": "Ryan", "id": "1228056572246532096"}, {"screen_name": "gtconway3d", "name": "George Conway🌻", "id": "471677441"}], "retweet_date": "", "translate": "", "trans_src": "", "trans_dest": ""},{"id": 1255268375007244291, "conversation_id": "1255258282492657664", "created_at": "2020-04-28 18:51:17 EDT", "date": "2020-04-28", "time": "18:51:17", "timezone": "-0500", "user_id": 847422670635323395, "username": "marlinsandes", "name": "Andes Marlins on mastodon @marlinsandes@qoto.org", "place": "", "tweet": "If true then consider actions towards solutions. The means are all here! It needs #solidarity All are by far the majority, if acting together, not the jargon 'minorities'. Even the small number in the position to act can team up. Revise, reform the 6 examples + #election process.", "language": "en", "mentions": [], "urls": [], "photos": [], "replies_count": 1, "retweets_count": 0, "likes_count": 0, "hashtags": ["solidarity", "election"], "cashtags": [], "link": "https://twitter.com/marlinsandes/status/1255268375007244291", "retweet": false, "quote_url": "", "video": 0, "thumbnail": "", "near": "", "geo": "", "source": "", "user_rt_id": "", "user_rt": "", "retweet_id": "", "reply_to": [], "retweet_date": "", "translate": "", "trans_src": "", "trans_dest": ""},{"id": 1255267974644150274, "conversation_id": "1255267439312605187", "created_at": "2020-04-28 18:49:41 EDT", "date": "2020-04-28", "time": "18:49:41", "timezone": "-0500", "user_id": 1214595640099033090, "username": "honestelections", "name": "Honest Elections Project", "place": "", "tweet": "A bipartisan election reform commission co-chaired by Pres. Jimmy Carter recommended protecting ballots from this sort of conduct by limiting who can handle them.   That’s what Arizona did—and the Democratic Party is suing to erase that safeguard.", "language": "en", "mentions": [], "urls": [], "photos": [], "replies_count": 1, "retweets_count": 0, "likes_count": 1, "hashtags": [], "cashtags": [], "link": "https://twitter.com/honestelections/status/1255267974644150274", "retweet": false, "quote_url": "", "video": 0, "thumbnail": "", "near": "", "geo": "", "source": "", "user_rt_id": "", "user_rt": "", "retweet_id": "", "reply_to": [], "retweet_date": "", "translate": "", "trans_src": "", "trans_dest": ""},{"id": 1255249263975632898, "conversation_id": "1255191823603171333", "created_at": "2020-04-28 17:35:20 EDT", "date": "2020-04-28", "time": "17:35:20", "timezone": "-0500", "user_id": 581948160, "username": "mhumler", "name": "Cincy Acolyte", "place": "", "tweet": "@tscinti @howardwilkinson I've heard of that. Hopefully concern about the virus spurs much needed election reform. Starting with a process like this, to ensure everyone who wants to vote has the opportunity to do so.", "language": "en", "mentions": [], "urls": [], "photos": [], "replies_count": 0, "retweets_count": 0, "likes_count": 1, "hashtags": [], "cashtags": [], "link": "https://twitter.com/MHumler/status/1255249263975632898", "retweet": false, "quote_url": "", "video": 0, "thumbnail": "", "near": "", "geo": "", "source": "", "user_rt_id": "", "user_rt": "", "retweet_id": "", "reply_to": [{"screen_name": "tscinti", "name": "Joe Metz", "id": "24685484"}, {"screen_name": "howardwilkinson", "name": "Howard Wilkinson", "id": "20059284"}], "retweet_date": "", "translate": "", "trans_src": "", "trans_dest": ""},{"id": 1255247953612230658, "conversation_id": "1255247953612230658", "created_at": "2020-04-28 17:30:08 EDT", "date": "2020-04-28", "time": "17:30:08", "timezone": "-0500", "user_id": 19405365, "username": "rslc", "name": "Republican State Leadership Committee", "place": "", "tweet": "Which state issues are you most concerned about this November?  ➡️Infrastructure ➡️Health Care ➡️ Tax Reform ➡️ Job Growth ➡️ Election Security  Take the survey now!  https://t.co/9bIFDbuQ8K", "language": "en", "mentions": [], "urls": ["https://secure.winred.com/republican-state-leadership-committee/state-issue/"], "photos": [], "replies_count": 0, "retweets_count": 1, "likes_count": 2, "hashtags": [], "cashtags": [], "link": "https://twitter.com/RSLC/status/1255247953612230658", "retweet": false, "quote_url": "", "video": 0, "thumbnail": "", "near": "", "geo": "", "source": "", "user_rt_id": "", "user_rt": "", "retweet_id": "", "reply_to": [], "retweet_date": "", "translate": "", "trans_src": "", "trans_dest": ""},{"id": 1255245746116464640, "conversation_id": "1254634515953258498", "created_at": "2020-04-28 17:21:21 EDT", "date": "2020-04-28", "time": "17:21:21", "timezone": "-0500", "user_id": 2852887700, "username": "psycophant", "name": "Deist After Dark", "place": "", "tweet": "@kiteie @Nancy_Crouse I may be confused by your comment on voting. I’m not sure if you were in favour of election reform or thankfull that it had not been addressed. That is what I was originally responding to but the actions of the parties don’t really relate. Two different issues.", "language": "en", "mentions": [], "urls": [], "photos": [], "replies_count": 0, "retweets_count": 0, "likes_count": 0, "hashtags": [], "cashtags": [], "link": "https://twitter.com/Psycophant/status/1255245746116464640", "retweet": false, "quote_url": "", "video": 0, "thumbnail": "", "near": "", "geo": "", "source": "", "user_rt_id": "", "user_rt": "", "retweet_id": "", "reply_to": [{"screen_name": "kiteie", "name": "Kitte - #LiberalBestGovernment (❁´◡`❁)", "id": "16270415"}, {"screen_name": "Nancy_Crouse", "name": "Nancy Crouse", "id": "1004022175"}], "retweet_date": "", "translate": "", "trans_src": "", "trans_dest": ""},{"id": 1255235802193375235, "conversation_id": "1255222158470586372", "created_at": "2020-04-28 16:41:51 EDT", "date": "2020-04-28", "time": "16:41:51", "timezone": "-0500", "user_id": 348168254, "username": "xxmastercj21xx", "name": "Shao", "place": "", "tweet": "@DFlamingold @SayNoToWeebs @Kayfabemusic1 @tjgilmour @hasanthehun Actively organizing wont do shit for THIS election cycle. Which really fucking matters. And if you argument was \"vote blue but also advocate and push for structural reform\" then I'd be all onboard. But no you think its allright to just let trump win while u try and \"organize\"", "language": "en", "mentions": [], "urls": [], "photos": [], "replies_count": 0, "retweets_count": 0, "likes_count": 0, "hashtags": [], "cashtags": [], "link": "https://twitter.com/xxMasterCJ21xx/status/1255235802193375235", "retweet": false, "quote_url": "", "video": 0, "thumbnail": "", "near": "", "geo": "", "source": "", "user_rt_id": "", "user_rt": "", "retweet_id": "", "reply_to": [{"screen_name": "Kayfabemusic1", "name": "Goth Brooks", "id": "1159634765542088705"}, {"screen_name": "tjgilmour", "name": "TJ", "id": "91462417"}, {"screen_name": "hasanthehun", "name": "hasanabi", "id": "326756275"}], "retweet_date": "", "translate": "", "trans_src": "", "trans_dest": ""},{"id": 1255232088619524100, "conversation_id": "1255230417772347398", "created_at": "2020-04-28 16:27:05 EDT", "date": "2020-04-28", "time": "16:27:05", "timezone": "-0500", "user_id": 1250024092838887429, "username": "binta_queenn", "name": "Rhamnus purshiana 🌿", "place": "", "tweet": "@john_danfulani Indeed. The only way to stop this evil act is through electoral reform.  Without electoral reform, just expect another TA TA TA election. Kogi and kano as a case study.  #electoralreform", "language": "en", "mentions": [], "urls": [], "photos": [], "replies_count": 0, "retweets_count": 0, "likes_count": 0, "hashtags": ["electoralreform"], "cashtags": [], "link": "https://twitter.com/binta_queenn/status/1255232088619524100", "retweet": false, "quote_url": "", "video": 0, "thumbnail": "", "near": "", "geo": "", "source": "", "user_rt_id": "", "user_rt": "", "retweet_id": "", "reply_to": [{"screen_name": "john_danfulani", "name": "john danfulani", "id": "764342549318406144"}], "retweet_date": "", "translate": "", "trans_src": "", "trans_dest": ""},{"id": 1255232031895797768, "conversation_id": "1255225295877091331", "created_at": "2020-04-28 16:26:52 EDT", "date": "2020-04-28", "time": "16:26:52", "timezone": "-0500", "user_id": 584999553, "username": "gbphs", "name": "Paul T Horgan", "place": "", "tweet": "@orr_robinson @Gabriel_Pogrund @SamLowry60 That still does not explain the appallingly poor turnout.  The Conservative Party leadership election was conducted by postal ballot and probably by the same organisation, Electoral Reform Services.  There is something wrong with union culture.", "language": "en", "mentions": [], "urls": [], "photos": [], "replies_count": 2, "retweets_count": 0, "likes_count": 0, "hashtags": [], "cashtags": [], "link": "https://twitter.com/GBPHS/status/1255232031895797768", "retweet": false, "quote_url": "", "video": 0, "thumbnail": "", "near": "", "geo": "", "source": "", "user_rt_id": "", "user_rt": "", "retweet_id": "", "reply_to": [{"screen_name": "orr_robinson", "name": "Alan Robinson-Orr 🏳️‍🌈 🇪🇺 🇺🇦 🇮🇪 🇬🇧 🏳️‍⚧", "id": "1199568588471984128"}, {"screen_name": "Gabriel_Pogrund", "name": "Gabriel Pogrund", "id": "404365807"}, {"screen_name": "SamLowry60", "name": "Sam Lowry", "id": "912229793739018240"}], "retweet_date": "", "translate": "", "trans_src": "", "trans_dest": ""},{"id": 1255227577012293632, "conversation_id": "1255224800164884482", "created_at": "2020-04-28 16:09:10 EDT", "date": "2020-04-28", "time": "16:09:10", "timezone": "-0500", "user_id": 1252244262936367106, "username": "zechari98425837", "name": "Zechariah", "place": "", "tweet": "@OfficialMLK3 My top 5 are: Artificial Intelligence American Imperialism Campaign Finance Reform Election Integrity Environmentally based policies", "language": "en", "mentions": [], "urls": [], "photos": [], "replies_count": 0, "retweets_count": 0, "likes_count": 0, "hashtags": [], "cashtags": [], "link": "https://twitter.com/Zechari98425837/status/1255227577012293632", "retweet": false, "quote_url": "", "video": 0, "thumbnail": "", "near": "", "geo": "", "source": "", "user_rt_id": "", "user_rt": "", "retweet_id": "", "reply_to": [{"screen_name": "OfficialMLK3", "name": "Martin Luther King III", "id": "2732591676"}], "retweet_date": "", "translate": "", "trans_src": "", "trans_dest": ""},{"id": 1255218588425818115, "conversation_id": "1255218588425818115", "created_at": "2020-04-28 15:33:26 EDT", "date": "2020-04-28", "time": "15:33:26", "timezone": "-0500", "user_id": 764315438679339008, "username": "amy_tobia", "name": "Amy Tobia", "place": "", "tweet": "Something good can still come out of 2020.  Election reform including Ranked Choice Voting might finally get the traction needed.  https://t.co/Euo0gtzZtG", "language": "en", "mentions": [], "urls": ["https://www.theatlantic.com/politics/archive/2020/04/2020-election-vote-by-mail-ranked-choice-caucuses/610780/"], "photos": [], "replies_count": 1, "retweets_count": 0, "likes_count": 1, "hashtags": [], "cashtags": [], "link": "https://twitter.com/amy_tobia/status/1255218588425818115", "retweet": false, "quote_url": "", "video": 0, "thumbnail": "", "near": "", "geo": "", "source": "", "user_rt_id": "", "user_rt": "", "retweet_id": "", "reply_to": [], "retweet_date": "", "translate": "", "trans_src": "", "trans_dest": ""},{"id": 1255218242630619139, "conversation_id": "1255193874617765888", "created_at": "2020-04-28 15:32:04 EDT", "date": "2020-04-28", "time": "15:32:04", "timezone": "-0500", "user_id": 1111416457370447872, "username": "leroybrwn2", "name": "Leroy Brown", "place": "", "tweet": "@k_govers @LindsayKempFan @AaronWherry Does it? That was the point of the Liberals claim of 2015 of voter reform as it is not a balanced representation per province. As seen in the last election, the Liberals are not as liked outside of places like the GTA where they spent huge amounts of money to buy votes.", "language": "en", "mentions": [], "urls": [], "photos": [], "replies_count": 2, "retweets_count": 0, "likes_count": 0, "hashtags": [], "cashtags": [], "link": "https://twitter.com/leroybrwn2/status/1255218242630619139", "retweet": false, "quote_url": "", "video": 0, "thumbnail": "", "near": "", "geo": "", "source": "", "user_rt_id": "", "user_rt": "", "retweet_id": "", "reply_to": [{"screen_name": "k_govers", "name": "Kees Govers", "id": "2806448879"}, {"screen_name": "LindsayKempFan", "name": "Not fit to print", "id": "73873854"}, {"screen_name": "AaronWherry", "name": "Aaron Wherry", "id": "18652307"}], "retweet_date": "", "translate": "", "trans_src": "", "trans_dest": ""},{"id": 1255216720240926720, "conversation_id": "1255152506155360259", "created_at": "2020-04-28 15:26:01 EDT", "date": "2020-04-28", "time": "15:26:01", "timezone": "-0500", "user_id": 16665097, "username": "glasspearl", "name": "Abigail 🇿🇦", "place": "", "tweet": "@g_stober @gopoboyk @RealityStriker @MaraMbewu It's not for the ANC to pass. The election reform case is still waiting for a decision by the ConCourt. It's case CCT110/19 if you want to follow it.", "language": "en", "mentions": [], "urls": [], "photos": [], "replies_count": 2, "retweets_count": 0, "likes_count": 2, "hashtags": [], "cashtags": [], "link": "https://twitter.com/GlassPearl/status/1255216720240926720", "retweet": false, "quote_url": "", "video": 0, "thumbnail": "", "near": "", "geo": "", "source": "", "user_rt_id": "", "user_rt": "", "retweet_id": "", "reply_to": [{"screen_name": "g_stober", "name": "Khosi I remain✌️", "id": "1218595160747139073"}, {"screen_name": "gopoboyk", "name": "Champion GBK", "id": "462690627"}, {"screen_name": "RealityStriker", "name": "Mkhwebane Must Be Jailed!", "id": "733609304322904064"}, {"screen_name": "MaraMbewu", "name": "👸Tee✊👊..", "id": "1045631283920089088"}], "retweet_date": "", "translate": "", "trans_src": "", "trans_dest": ""},{"id": 1255206872568803328, "conversation_id": "1254783039642595330", "created_at": "2020-04-28 14:46:53 EDT", "date": "2020-04-28", "time": "14:46:53", "timezone": "-0500", "user_id": 112954185, "username": "richinmn", "name": "Oblong Muskie in MN", "place": "", "tweet": "@anarchosocial @bourgeoisalien @GovJVentura He took over the Reform Party in MN and left it shortly after the election because they wouldn’t give him control of the party. He also talked about leaving office early because he wasn’t interested anymore.", "language": "en", "mentions": [], "urls": [], "photos": [], "replies_count": 0, "retweets_count": 0, "likes_count": 0, "hashtags": [], "cashtags": [], "link": "https://twitter.com/RichinMN/status/1255206872568803328", "retweet": false, "quote_url": "", "video": 0, "thumbnail": "", "near": "", "geo": "", "source": "", "user_rt_id": "", "user_rt": "", "retweet_id": "", "reply_to": [{"screen_name": "anarchosocial", "name": "Comrade Questions", "id": "916239959539027968"}, {"screen_name": "bourgeoisalien", "name": "beth, an alien", "id": "2396910715"}, {"screen_name": "GovJVentura", "name": "Jesse Ventura", "id": "2218177956"}], "retweet_date": "", "translate": "", "trans_src": "", "trans_dest": ""},{"id": 1255194091039731714, "conversation_id": "1255194089961766914", "created_at": "2020-04-28 13:56:06 EDT", "date": "2020-04-28", "time": "13:56:06", "timezone": "-0500", "user_id": 1123963660395786241, "username": "smart_elections", "name": "SMART Elections", "place": "", "tweet": "Meanwhile we received this link via @IssueOneReform, a great group working on #ElectionReform. The last round of funding called \"CARES\" does come w/ restrictions on how election funds can be spent. We are researching these to evaluate their effectiveness.  https://t.co/SKKirSPGXz", "language": "en", "mentions": [{"screen_name": "issueonereform", "name": "issue one", "id": "17547736"}], "urls": ["https://www.eac.gov/election-officials/guidance-use-hava-funds-expenses-related-covid-19"], "photos": [], "replies_count": 1, "retweets_count": 2, "likes_count": 1, "hashtags": ["electionreform"], "cashtags": [], "link": "https://twitter.com/SMART_elections/status/1255194091039731714", "retweet": false, "quote_url": "", "video": 0, "thumbnail": "", "near": "", "geo": "", "source": "", "user_rt_id": "", "user_rt": "", "retweet_id": "", "reply_to": [], "retweet_date": "", "translate": "", "trans_src": "", "trans_dest": ""},{"id": 1255185885051736067, "conversation_id": "1255184485458608128", "created_at": "2020-04-28 13:23:29 EDT", "date": "2020-04-28", "time": "13:23:29", "timezone": "-0500", "user_id": 313458732, "username": "brendanowicz", "name": "overall deal inker", "place": "", "tweet": "instead of running for another office after the gubernatorial election she became an advocate for the completely uncontroversial issue of election reform, staying out of every other intra-party policy debate, and took $5M from Mike Bloomberg. Pass!", "language": "en", "mentions": [], "urls": [], "photos": [], "replies_count": 0, "retweets_count": 0, "likes_count": 5, "hashtags": [], "cashtags": [], "link": "https://twitter.com/brendanowicz/status/1255185885051736067", "retweet": false, "quote_url": "", "video": 0, "thumbnail": "", "near": "", "geo": "", "source": "", "user_rt_id": "", "user_rt": "", "retweet_id": "", "reply_to": [], "retweet_date": "", "translate": "", "trans_src": "", "trans_dest": ""},{"id": 1255180803572670465, "conversation_id": "1255180803572670465", "created_at": "2020-04-28 13:03:18 EDT", "date": "2020-04-28", "time": "13:03:18", "timezone": "-0500", "user_id": 885649502, "username": "kevinjryanjr", "name": "Kevin J. Ryan", "place": "", "tweet": "#Queens voters have been denied their voice as the special election for #QueensBP is canceled- again. Veteran prosecutor @QuinnforQueens is a fine candidate, expert in the dangerous consequences of the Democrats’ “bail reform” that sets us back to the Dinkins Death Wish Days", "language": "en", "mentions": [], "urls": [], "photos": [], "replies_count": 0, "retweets_count": 1, "likes_count": 1, "hashtags": ["queens", "queensbp"], "cashtags": [], "link": "https://twitter.com/KevinJRyanJr/status/1255180803572670465", "retweet": false, "quote_url": "", "video": 0, "thumbnail": "", "near": "", "geo": "", "source": "", "user_rt_id": "", "user_rt": "", "retweet_id": "", "reply_to": [], "retweet_date": "", "translate": "", "trans_src": "", "trans_dest": ""},{"id": 1255180610185854981, "conversation_id": "1255180610185854981", "created_at": "2020-04-28 13:02:32 EDT", "date": "2020-04-28", "time": "13:02:32", "timezone": "-0500", "user_id": 921728354, "username": "jarrettblanc", "name": "Jarrett Blanc", "place": "", "tweet": "That's true. Winner-take-all elections for a highly empowered President in an (on paper) centralized state don't work for Afghanistan. Every election since '04 has undermined the government. I have repeatedly advised reform prior to more elections. '19 elections support my case.", "language": "en", "mentions": [], "urls": [], "photos": [], "replies_count": 8, "retweets_count": 14, "likes_count": 36, "hashtags": [], "cashtags": [], "link": "https://twitter.com/JarrettBlanc/status/1255180610185854981", "retweet": false, "quote_url": "https://twitter.com/AISS_Afg/status/1255177107661115398", "video": 0, "thumbnail": "", "near": "", "geo": "", "source": "", "user_rt_id": "", "user_rt": "", "retweet_id": "", "reply_to": [], "retweet_date": "", "translate": "", "trans_src": "", "trans_dest": ""},{"id": 1255157338878742535, "conversation_id": "1255157338878742535", "created_at": "2020-04-28 11:30:03 EDT", "date": "2020-04-28", "time": "11:30:03", "timezone": "-0500", "user_id": 87532425, "username": "koreaeconinst", "name": "KEI", "place": "", "tweet": "South Korea adopted a new election system for distributing legislative seats with the intention of making politics more inclusive. But will it work? Not unless the two major parties continue bypassing the reform through a loophole. #PeninsulaBlog  https://t.co/ezKAWrCAfp", "language": "en", "mentions": [], "urls": ["http://blog.keia.org/2020/04/how-does-south-koreas-new-election-system-work/"], "photos": [], "replies_count": 0, "retweets_count": 0, "likes_count": 1, "hashtags": ["peninsulablog"], "cashtags": [], "link": "https://twitter.com/KoreaEconInst/status/1255157338878742535", "retweet": false, "quote_url": "", "video": 0, "thumbnail": "", "near": "", "geo": "", "source": "", "user_rt_id": "", "user_rt": "", "retweet_id": "", "reply_to": [], "retweet_date": "", "translate": "", "trans_src": "", "trans_dest": ""},{"id": 1255150623617474560, "conversation_id": "1255148658846076930", "created_at": "2020-04-28 11:03:22 EDT", "date": "2020-04-28", "time": "11:03:22", "timezone": "-0500", "user_id": 325385270, "username": "jysexton", "name": "Jared Yates Sexton", "place": "", "tweet": "Election reform is hard enough because it's a complicated and unnecessarily partisan issue. Republicans can only win if turnout is low and Americans are disenfranchised. Making the 2020 Election happen would be a vicious fight even if one party didn't benefit from dragging feet.", "language": "en", "mentions": [], "urls": [], "photos": [], "replies_count": 0, "retweets_count": 28, "likes_count": 80, "hashtags": [], "cashtags": [], "link": "https://twitter.com/JYSexton/status/1255150623617474560", "retweet": false, "quote_url": "", "video": 0, "thumbnail": "", "near": "", "geo": "", "source": "", "user_rt_id": "", "user_rt": "", "retweet_id": "", "reply_to": [], "retweet_date": "", "translate": "", "trans_src": "", "trans_dest": ""}]